{
  "en": {
    "welcome": "Welcome to LifeLine AI",
    "tagline": "Your AI-powered Community Healthcare Assistant",
    "askSymptoms": "Describe your symptoms or health concern",
    "emergency": "Emergency",
    "callEmergency": "Call Emergency Services",
    "nearbyHospitals": "Nearby Hospitals",
    "govSchemes": "Government Health Schemes",
    "medicines": "Medicine Information",
    "followUp": "Follow-up Care",
    "actionPlan": "Your Action Plan",
    "age": "Age",
    "gender": "Gender",
    "male": "Male",
    "female": "Female",
    "other": "Other",
    "location": "Location",
    "submit": "Submit",
    "loading": "Analyzing your health concern...",
    "healthAssessment": "Health Assessment",
    "urgencyLow": "Low Urgency - Self Care",
    "urgencyMedium": "Medium Urgency - Visit Doctor",
    "urgencyHigh": "High Urgency - Seek Immediate Care",
    "urgencyCritical": "CRITICAL - Emergency",
    "viewDetails": "View Details",
    "applyNow": "Apply Now",
    "setReminder": "Set Reminder",
    "translate": "Translate",
    "analytics": "Community Analytics",
    "chat": "Chat",
    "dashboard": "Dashboard",
    "profile": "Profile",
    "settings": "Settings",
    "languageSelect": "Select Language",
    "startConsultation": "Start Consultation",
    "disclaimer": "This is for educational purposes only. Always consult a healthcare professional.",
    "existingConditions": "Existing Conditions",
    "name": "Name",
    "income": "Annual Income",
    "occupation": "Occupation",
    "symptoms": "Symptoms",
    "possibleCauses": "Possible Causes",
    "selfCare": "Self Care Advice",
    "seekMedicalHelp": "When to Seek Medical Help",
    "eligibleSchemes": "Eligible Schemes",
    "documentsRequired": "Documents Required",
    "howItWorks": "How It Works",
    "agents": "AI Agents",
    "available": "Available",
    "free": "Free",
    "home": "Home",
    "schemes": "Schemes",
    "history": "History",
    "logout": "Logout",
    "heroTitle": "Talk to LifeLine AI – Smarter, Faster, Better",
    "tryItNow": "Try it now",
    "getInTouch": "Get in touch",
    "contactDesc": "Got questions or need assistance? LifeLine AI is here to help. Reach out and we'll get back to you as soon as possible.",
    "contactUs": "Contact us",
    "email": "Email",
    "all": "All",
    "cancel": "Cancel",
    "phone": "Phone",
    "warning": "Warning",
    "processing": "Processing...",
    "ready": "Ready",
    "active": "Active",
    "done": "Done",
    "total": "Total",
    "setYourProfile": "Set Your Profile",
    "locationNotSet": "Location not set",
    "quickProfile": "Quick Profile",
    "selectCity": "Select City",
    "saveProfile": "Save Profile",
    "schemesHeader": "Government Health Schemes Navigator",
    "schemesSubtitle": "Explore medical financial aid, maternity support, and free immunization plans.",
    "searchPlaceholder": "Search schemes by name or keywords...",
    "stateRegion": "State Region",
    "allIndia": "All India",
    "genderSpecific": "Gender Specific",
    "allGenders": "All Genders",
    "femaleOnly": "Female Only",
    "maleOnly": "Male Only",
    "benefitCategory": "Benefit Category",
    "foundSchemesCount": "Found {count} matching health benefit program(s)",
    "eligibilityCriteria": "Eligibility Criteria:",
    "incomeLimit": "Income Limit:",
    "ageGroup": "Age Group:",
    "genderTarget": "Gender target:",
    "applicableStates": "Applicable States:",
    "documentsNeeded": "Documents Needed to Apply:",
    "tollFree": "Toll-Free Helpline:",
    "applyOnline": "Apply Online ↗",
    "categoryGeneralHealth": "General Health",
    "categoryMaternalChild": "Maternal & Child Care",
    "categoryNutrition": "Nutrition",
    "categoryMentalHealth": "Mental Health",
    "categorySpecialized": "Specialized Procedures",
    "categoryInsurance": "Insurance & Security",
    "medicalHistoryTitle": "Medical History",
    "medicalHistorySubtitle": "Your past consultations and health records",
    "noConsultations": "No Consultations Yet",
    "noConsultationsDesc": "Your medical history will appear here after you complete your first AI-powered health consultation.",
    "startConsultationMH": "Start a Consultation",
    "clearHistory": "Clear History",
    "consultationCount": "{count} consultation",
    "consultationCountPlural": "{count} consultations",
    "clearHistoryConfirm": "Clear Medical History?",
    "clearHistoryDesc": "This will permanently delete all {count} consultation records. This action cannot be undone.",
    "clearHistoryDescSingle": "This will permanently delete your consultation record. This action cannot be undone.",
    "deleteAll": "Delete All",
    "symptomsLabel": "Symptoms:",
    "hideDetails": "Hide Details",
    "viewActionPlan": "View Action Plan",
    "communityTrendsHeader": "Community Health & Agent Analytics",
    "communityTrendsSubtitle": "Real-time statistics on AI system coordination and community concerns.",
    "totalHealthQueries": "Total Health Queries",
    "agentsOperational": "Agents Operational",
    "avgCoordinationTime": "Avg Coordination Time",
    "emergenciesFlagged": "Emergencies Flagged",
    "trendsHeader": "Community Health Concern Trends",
    "trendsDesc": "Anonymized symptom tracking for district healthcare response.",
    "cases": "cases",
    "districtAlert": "District Alert:",
    "districtAlertText": "Malaria/Dengue season. Mosquito control suggested in Karimnagar/Warangal districts.",
    "recentConsultationsHeader": "Your Recent Consultations",
    "noConsultationsLogged": "No consultations logged yet.",
    "startChattingTip": "Start chatting with LifeLine AI to generate your health assessments.",
    "quickActions": "Quick Actions",
    "startSymptomCheckTitle": "Start Symptom Check",
    "startSymptomCheckDesc": "Describe your issue and get guidance.",
    "browseGovSchemesTitle": "Browse Govt Schemes",
    "browseGovSchemesDesc": "Check eligibility for state & national plans.",
    "downloadOfflineDbTitle": "Download Offline DB",
    "downloadOfflineDbDesc": "Save healthcare listings to phone storage.",
    "actionPlanHeader": "Personalized Health Action Plan",
    "urgencyLevel": "{urgency} Urgency",
    "emergencyResponse": "Emergency Critical Response",
    "callAmbulance": "CALL AMBULANCE",
    "immediateActions": "Immediate Actions Required:",
    "symptomAssessment": "Symptom & Health Assessment",
    "matchedSymptoms": "Matched Symptoms:",
    "possibleConditions": "Possible Conditions:",
    "careInstructions": "Care Instructions:",
    "seekMedicalCareIf": "Seek immediate medical care if you experience:",
    "nearbyFacilities": "Nearby Healthcare Facilities",
    "liveWebSearch": "Live Web Search 🌐",
    "beds": "Beds:",
    "emergency247": "Emergency 24/7",
    "ayushmanBharatTag": "Ayushman Bharat",
    "govBenefits": "Government Health Benefits",
    "eligibilityStrong": "Eligibility:",
    "requiredDocs": "Required Documents:",
    "medicineReference": "Medicine Reference & Education",
    "usageLabel": "Usage:",
    "dosageLabel": "Dosage:",
    "warningLabel": "Warning:",
    "generalMedGuidelines": "General Medicine Guidelines",
    "followupCare": "Follow-up Care & Timelines",
    "healthReminders": "Health Reminders Timeline:",
    "monitoringChecklist": "Health Monitoring Checklist",
    "printActionPlan": "Print Action Plan",
    "saveToProfile": "Save to Profile",
    "orchestrator": "Orchestrator",
    "multiAgentPipeline": "Multi-Agent Pipeline",
    "analyzing": "Analyzing...",
    "doneIn": "Done in",
    "standby": "Standby",
    "parallelProcessingTip": "Agents process in parallel with intelligent routing"
  },
  "hi": {
    "welcome": "लाइफलाइन AI में आपका स्वागत है",
    "tagline": "आपका AI-संचालित सामुदायिक स्वास्थ्य सहायक",
    "askSymptoms": "अपने लक्षण या स्वास्थ्य समस्या बताएं",
    "emergency": "आपातकालीन",
    "callEmergency": "आपातकालीन सेवाओं को कॉल करें",
    "nearbyHospitals": "नजदीकी अस्पताल",
    "govSchemes": "सरकारी स्वास्थ्य योजनाएं",
    "medicines": "दवा की जानकारी",
    "followUp": "फॉलो-अप देखभाल",
    "actionPlan": "आपकी कार्य योजना",
    "age": "आयु",
    "gender": "लिंग",
    "male": "पुरुष",
    "female": "महिला",
    "other": "अन्य",
    "location": "स्थान",
    "submit": "जमा करें",
    "loading": "आपकी स्वास्थ्य समस्या का विश्लेषण...",
    "healthAssessment": "स्वास्थ्य मूल्यांकन",
    "urgencyLow": "कम तात्कालिकता - स्वयं देखभाल",
    "urgencyMedium": "मध्यम तात्कालिकता - डॉक्टर से मिलें",
    "urgencyHigh": "उच्च तात्कालिकता - तुरंत चिकित्सा लें",
    "urgencyCritical": "गंभीर - आपातकालीन",
    "viewDetails": "विवरण देखें",
    "applyNow": "अभी आवेदन करें",
    "setReminder": "रिमाइंडर सेट करें",
    "translate": "अनुवाद करें",
    "analytics": "सामुदायिक विश्लेषण",
    "chat": "चैट",
    "dashboard": "डैशबोर्ड",
    "profile": "प्रोफाइल",
    "settings": "सेटिंग्स",
    "languageSelect": "भाषा चुनें",
    "startConsultation": "परामर्श शुरू करें",
    "disclaimer": "यह केवल शैक्षिक उद्देश्यों के लिए है। हमेशा स्वास्थ्य पेशेवर से परामर्श करें।",
    "existingConditions": "मौजूदा बीमारियाँ",
    "name": "नाम",
    "income": "वार्षिक आय",
    "occupation": "पेशा",
    "symptoms": "लक्षण",
    "possibleCauses": "संभावित कारण",
    "selfCare": "स्वयं देखभाल सलाह",
    "seekMedicalHelp": "चिकित्सा सहायता कब लें",
    "eligibleSchemes": "पात्र योजनाएं",
    "documentsRequired": "आवश्यक दस्तावेज",
    "howItWorks": "यह कैसे काम करता है",
    "agents": "AI एजेंट",
    "available": "उपलब्ध",
    "free": "मुफ्त",
    "home": "होम",
    "schemes": "योजनाएं",
    "history": "इतिहास",
    "logout": "लॉगआउट",
    "heroTitle": "लाइफलाइन AI से बात करें – अधिक स्मार्ट, अधिक तेज़, अधिक बेहतर",
    "tryItNow": "अभी आज़माएं",
    "getInTouch": "संपर्क करें",
    "contactDesc": "कोई प्रश्न हैं या सहायता की आवश्यकता है? लाइफलाइन AI मदद के लिए यहाँ है। संपर्क करें और हम जल्द से जल्द आपसे संपर्क करेंगे।",
    "contactUs": "संपर्क करें",
    "email": "ईमेल",
    "all": "सभी",
    "cancel": "रद्द करें",
    "phone": "फ़ोन",
    "warning": "चेतावनी",
    "processing": "प्रसंस्करण...",
    "ready": "तैयार",
    "active": "सक्रिय",
    "done": "पूर्ण",
    "total": "कुल",
    "setYourProfile": "अपनी प्रोफाइल सेट करें",
    "locationNotSet": "स्थान निर्धारित नहीं है",
    "quickProfile": "त्वरित प्रोफाइल",
    "selectCity": "शहर चुनें",
    "saveProfile": "प्रोफाइल सहेजें",
    "schemesHeader": "सरकारी स्वास्थ्य योजनाएं नेविगेटर",
    "schemesSubtitle": "चिकित्सा वित्तीय सहायता, मातृत्व सहायता और मुफ्त टीकाकरण योजनाओं का पता लगाएं।",
    "searchPlaceholder": "नाम या कीवर्ड द्वारा योजनाओं को खोजें...",
    "stateRegion": "राज्य क्षेत्र",
    "allIndia": "अखिल भारतीय",
    "genderSpecific": "विशेष लिंग",
    "allGenders": "सभी लिंग",
    "femaleOnly": "केवल महिला",
    "maleOnly": "केवल पुरुष",
    "benefitCategory": "लाभ श्रेणी",
    "foundSchemesCount": "{count} मिलान स्वास्थ्य लाभ कार्यक्रम मिले",
    "eligibilityCriteria": "पात्रता मापदंड:",
    "incomeLimit": "आय सीमा:",
    "ageGroup": "आयु समूह:",
    "genderTarget": "लक्षित लिंग:",
    "applicableStates": "लागू राज्य:",
    "documentsNeeded": "आवेदन करने के लिए आवश्यक दस्तावेज:",
    "tollFree": "टोल-फ्री हेल्पलाइन:",
    "applyOnline": "ऑनलाइन आवेदन करें ↗",
    "categoryGeneralHealth": "सामान्य स्वास्थ्य",
    "categoryMaternalChild": "मातृत्व एवं शिशु देखभाल",
    "categoryNutrition": "पोषण",
    "categoryMentalHealth": "मानसिक स्वास्थ्य",
    "categorySpecialized": "विशेष प्रक्रियाएं",
    "categoryInsurance": "बीमा और सुरक्षा",
    "medicalHistoryTitle": "चिकित्सा इतिहास",
    "medicalHistorySubtitle": "आपके पिछले परामर्श और स्वास्थ्य रिकॉर्ड",
    "noConsultations": "अभी तक कोई परामर्श नहीं",
    "noConsultationsDesc": "अपना पहला एआई-संचालित स्वास्थ्य परामर्श पूरा करने के बाद आपका चिकित्सा इतिहास यहां दिखाई देगा।",
    "startConsultationMH": "परामर्श शुरू करें",
    "clearHistory": "इतिहास साफ़ करें",
    "consultationCount": "{count} परामर्श",
    "consultationCountPlural": "{count} परामर्श",
    "clearHistoryConfirm": "चिकित्सा इतिहास साफ़ करें?",
    "clearHistoryDesc": "यह स्थायी रूप से सभी {count} परामर्श रिकॉर्ड हटा देगा। इस कार्रवाई को पूर्ववत नहीं किया जा सकता है।",
    "clearHistoryDescSingle": "यह स्थायी रूप से आपका परामर्श रिकॉर्ड हटा देगा। इस कार्रवाई को पूर्ववत नहीं किया जा सकता है।",
    "deleteAll": "सभी हटाएं",
    "symptomsLabel": "लक्षण:",
    "hideDetails": "विवरण छिपाएं",
    "viewActionPlan": "कार्य योजना देखें",
    "communityTrendsHeader": "सामुदायिक स्वास्थ्य और एजेंट विश्लेषण",
    "communityTrendsSubtitle": "एआई सिस्टम समन्वय और सामुदायिक चिंताओं पर वास्तविक समय के आंकड़े।",
    "totalHealthQueries": "कुल स्वास्थ्य प्रश्न",
    "agentsOperational": "सक्रिय एजेंट",
    "avgCoordinationTime": "औसत समन्वय समय",
    "emergenciesFlagged": "चिह्नित आपातकाल",
    "trendsHeader": "सामुदायिक स्वास्थ्य चिंता रुझान",
    "trendsDesc": "जिला स्वास्थ्य प्रतिक्रिया के लिए अनाम लक्षण ट्रैकिंग।",
    "cases": "मामले",
    "districtAlert": "जिला अलर्ट:",
    "districtAlertText": "मलेरिया/डेंगू का मौसम। करीमनगर/वरंगल जिलों में मच्छर नियंत्रण का सुझाव।",
    "recentConsultationsHeader": "आपके हालिया परामर्श",
    "noConsultationsLogged": "अभी तक कोई परामर्श लॉग नहीं किया गया है।",
    "startChattingTip": "अपने स्वास्थ्य मूल्यांकन उत्पन्न करने के लिए लाइफलाइन एआई के साथ चैट करना शुरू करें।",
    "quickActions": "त्वरित कार्रवाई",
    "startSymptomCheckTitle": "लक्षण जांच शुरू करें",
    "startSymptomCheckDesc": "अपनी समस्या का वर्णन करें और मार्गदर्शन प्राप्त करें।",
    "browseGovSchemesTitle": "सरकारी योजनाओं को ब्राउज़ करें",
    "browseGovSchemesDesc": "राज्य और राष्ट्रीय योजनाओं के लिए पात्रता जांचें।",
    "downloadOfflineDbTitle": "ऑफ़लाइन डेटाबेस डाउनलोड करें",
    "downloadOfflineDbDesc": "स्वास्थ्य सेवा सूचियों को फोन स्टोरेज में सहेजें।",
    "actionPlanHeader": "व्यक्तिगत स्वास्थ्य कार्य योजना",
    "urgencyLevel": "{urgency} तात्कालिकता",
    "emergencyResponse": "आपातकालीन गंभीर प्रतिक्रिया",
    "callAmbulance": "एम्बुलेंस को बुलाओ",
    "immediateActions": "तत्काल आवश्यक कार्रवाई:",
    "symptomAssessment": "लक्षण और स्वास्थ्य मूल्यांकन",
    "matchedSymptoms": "मिलान लक्षण:",
    "possibleConditions": "संभावित स्थितियां:",
    "careInstructions": "देखभाल निर्देश:",
    "seekMedicalCareIf": "यदि आप अनुभव करते हैं तो तुरंत चिकित्सा देखभाल लें:",
    "nearbyFacilities": "नजदीकी स्वास्थ्य सुविधाएं",
    "liveWebSearch": "लाइव वेब खोज 🌐",
    "beds": "बिस्तर:",
    "emergency247": "आपातकालीन 24/7",
    "ayushmanBharatTag": "आयुष्मान भारत",
    "govBenefits": "सरकारी स्वास्थ्य लाभ",
    "eligibilityStrong": "पात्रता:",
    "requiredDocs": "आवश्यक दस्तावेज:",
    "medicineReference": "दवा संदर्भ और शिक्षा",
    "usageLabel": "उपयोग:",
    "dosageLabel": "खुराक:",
    "warningLabel": "चेतावनी:",
    "generalMedGuidelines": "सामान्य चिकित्सा दिशानिर्देश",
    "followupCare": "फॉलो-अप देखभाल और समयसीमा",
    "healthReminders": "स्वास्थ्य अनुस्मारक समयरेखा:",
    "monitoringChecklist": "स्वास्थ्य निगरानी चेकलिस्ट",
    "printActionPlan": "कार्य योजना प्रिंट करें",
    "saveToProfile": "प्रोफाइल में सहेजें",
    "orchestrator": "ऑर्केस्ट्रेटर",
    "multiAgentPipeline": "मल्टी-एजेंट पाइपलाइन",
    "analyzing": "विश्लेषण किया जा रहा है...",
    "doneIn": "में पूर्ण",
    "standby": "स्टैंडबाय",
    "parallelProcessingTip": "एजेंट बुद्धिमान रूटिंग के साथ समानांतर में प्रसंस्करण करते हैं"
  },
  "te": {
    "welcome": "లైఫ్‌లైన్ AI కి స్వాగతం",
    "tagline": "మీ AI-ఆధారిత సమాజ ఆరోగ్య సహాయకుడు",
    "askSymptoms": "మీ లక్షణాలను లేదా ఆరోగ్య సమస్యను వివరించండి",
    "emergency": "అత్యవసరం",
    "callEmergency": "అత్యవసర సేవలకు కాల్ చేయండి",
    "nearbyHospitals": "సమీపంలోని ఆసుపత్రులు",
    "govSchemes": "ప్రభుత్వ ఆరోగ్య పథకాలు",
    "medicines": "ఔషధ సమాచారం",
    "followUp": "ఫాలో-అప్ సంరక్షణ",
    "actionPlan": "మీ కార్యాచరణ ప్రణాళిక",
    "age": "వయస్సు",
    "gender": "లింగం",
    "male": "పురుషుడు",
    "female": "స్త్రీ",
    "other": "ఇతర",
    "location": "ప్రదేశం",
    "submit": "సమర్పించండి",
    "loading": "మీ ఆరోగ్య సమస్యను విశ్లేషిస్తోంది...",
    "healthAssessment": "ఆరోగ్య అంచనా",
    "urgencyLow": "తక్కువ అత్యవసరం - స్వీయ సంరక్షణ",
    "urgencyMedium": "మధ్యస్థ అత్యవసరం - వైద్యుడిని సందర్శించండి",
    "urgencyHigh": "అధిక అత్యవసరం - తక్షణ చికిత్స పొందండి",
    "urgencyCritical": "క్రిటికల్ - అత్యవసరం",
    "viewDetails": "వివరాలు చూడండి",
    "applyNow": "ఇప్పుడు దరఖాస్తు చేయండి",
    "setReminder": "రిమైండర్ సెట్ చేయండి",
    "translate": "అనువాదం",
    "analytics": "సమాజ విశ్లేషణ",
    "chat": "చాట్",
    "dashboard": "డాష్‌బోర్డ్",
    "profile": "ప్రొఫైల్",
    "settings": "సెట్టింగ్‌లు",
    "languageSelect": "భాష ఎంచుకోండి",
    "startConsultation": "సంప్రదింపు ప్రారంభించండి",
    "disclaimer": "ఇది విద్యా ప్రయోజనాల కోసం మాత్రమే. ఎల్లప్పుడూ ఆరోగ్య నిపుణులను సంప్రదించండి.",
    "existingConditions": "ఇప్పటికే ఉన్న వ్యాధులు",
    "name": "పేరు",
    "income": "వార్షిక ఆదాయం",
    "occupation": "వృత్తి",
    "symptoms": "లక్షణాలు",
    "possibleCauses": "సాధ్యమైన కారణాలు",
    "selfCare": "స్వీయ సంరక్షణ సలహా",
    "seekMedicalHelp": "వైద్య సహాయం ఎప్పుడు తీసుకోవాలి",
    "eligibleSchemes": "అర్హత ఉన్న పథకాలు",
    "documentsRequired": "అవసరమైన పత్రాలు",
    "howItWorks": "ఇది ఎలా పని చేస్తుంది",
    "agents": "AI ఏజెంట్లు",
    "available": "అందుబాటులో",
    "free": "ఉచితం",
    "home": "హోమ్",
    "schemes": "పథకాలు",
    "history": "చరిత్ర",
    "logout": "లాగ్అవుట్",
    "heroTitle": "లైఫ్‌లైన్ AI తో మాట్లాడండి – మరింత స్మార్ట్, మరింత వేగవంతం, మరింత మెరుగైనది",
    "tryItNow": "ఇప్పుడే ప్రయత్నించండి",
    "getInTouch": "సంప్రదించండి",
    "contactDesc": "ఏవైనా ప్రశ్నలు ఉన్నాయా లేదా సహాయం కావాలా? సహాయం చేయడానికి లైఫ్‌లైన్ AI ఇక్కడ ఉంది. సంప్రదించండి మరియు మేము వీలైనంత త్వరగా మిమ్మల్ని సంప్రదిస్తాము.",
    "contactUs": "మమ్మల్ని సంప్రదించండి",
    "email": "ఈమెయిల్",
    "all": "అన్నీ",
    "cancel": "రద్దు చేయి",
    "phone": "ఫోన్",
    "warning": "హెచ్చరిక",
    "processing": "ప్రాసెస్ అవుతోంది...",
    "ready": "సిద్ధంగా ఉంది",
    "active": "క్రియాశీల",
    "done": "పూర్తయింది",
    "total": "మొత్తం",
    "setYourProfile": "మీ ప్రొఫైల్‌ను సెట్ చేయండి",
    "locationNotSet": "స్థానం సెట్ చేయబడలేదు",
    "quickProfile": "త్వరిత ప్రొఫైల్",
    "selectCity": "నగరాన్ని ఎంచుకోండి",
    "saveProfile": "ప్రొఫైల్ సేవ్ చేయి",
    "schemesHeader": "ప్రభుత్వ ఆరోగ్య పథకాల నావిగేటర్",
    "schemesSubtitle": "వైద్య ఆర్థిక సహాయం, మాతృత్వ సహాయం మరియు ఉచిత టీకా పథకాలను అన్వేషించండి.",
    "searchPlaceholder": "పేరు లేదా కీవర్డ్ ద్వారా పథకాలను శోధించండి...",
    "stateRegion": "రాష్ట్ర ప్రాంతం",
    "allIndia": "అఖిల భారతదేశం",
    "genderSpecific": "లింగ నిర్దిష్ట",
    "allGenders": "అన్ని లింగాలు",
    "femaleOnly": "మహిళలు మాత్రమే",
    "maleOnly": "పురుషులు మాత్రమే",
    "benefitCategory": "ప్రయోజన వర్గం",
    "foundSchemesCount": "{count} సరిపోలే ఆరోగ్య ప్రయోజన కార్యక్రమాలు కనుగొనబడ్డాయి",
    "eligibilityCriteria": "అర్హత ప్రమాణాలు:",
    "incomeLimit": "ఆదాయ పరిమితి:",
    "ageGroup": "వయస్సు సమూహం:",
    "genderTarget": "లక్ష్య లింగం:",
    "applicableStates": "వర్తించే రాష్ట్రాలు:",
    "documentsNeeded": "దరఖాస్తు చేయడానికి అవసరమైన పత్రాలు:",
    "tollFree": "టోల్-ఫ్రీ హెల్ప్‌లైన్:",
    "applyOnline": "ఆన్‌లైన్‌లో దరఖాస్తు చేసుకోండి ↗",
    "categoryGeneralHealth": "సాధారణ ఆరోగ్యం",
    "categoryMaternalChild": "మాతృ మరియు శిశు సంరక్షణ",
    "categoryNutrition": "పోషకాహారం",
    "categoryMentalHealth": "మానసిక ఆరోగ్యం",
    "categorySpecialized": "ప్రత్యేక విధానాలు",
    "categoryInsurance": "భీమా & భద్రత",
    "medicalHistoryTitle": "వైద్య చరిత్ర",
    "medicalHistorySubtitle": "మీ గత సంప్రదింపులు మరియు ఆరోగ్య రికార్డులు",
    "noConsultations": "ఇంకా సంప్రదింపులు లేవు",
    "noConsultationsDesc": "మీరు మీ మొదటి AI-ఆధారిత ఆరోగ్య సంప్రదింపులను పూర్తి చేసిన తర్వాత మీ వైద్య చరిత్ర ఇక్కడ కనిపిస్తుంది.",
    "startConsultationMH": "సంప్రదింపు ప్రారంభించండి",
    "clearHistory": "చరిత్రను క్లియర్ చేయండి",
    "consultationCount": "{count} సంప్రదింపు",
    "consultationCountPlural": "{count} సంప్రదింపులు",
    "clearHistoryConfirm": "వైద్య చరిత్రను క్లియర్ చేయాలా?",
    "clearHistoryDesc": "ఇది అన్ని {count} సంప్రదింపు రికార్డులను శాశ్వతంగా తొలగిస్తుంది. ఈ చర్యను రద్దు చేయలేము.",
    "clearHistoryDescSingle": "ఇది మీ సంప్రదింపు రికార్డును శాశ్వతంగా తొలగిస్తుంది. ఈ చర్యను రద్దు చేయలేము.",
    "deleteAll": "అన్నీ తొలగించు",
    "symptomsLabel": "లక్షణాలు:",
    "hideDetails": "వివరాలను దాచు",
    "viewActionPlan": "కార్యాచరణ ప్రణాళికను చూడండి",
    "communityTrendsHeader": "కమ్యూనిటీ హెల్త్ & ఏజెంట్ అనలిటిక్స్",
    "communityTrendsSubtitle": "AI సిస్టమ్ సమన్వయం మరియు కమ్యూనిటీ ఆందోళనలపై నిజ-సమయ గణాంకాలు.",
    "totalHealthQueries": "మొత్తం ఆరోగ్య ప్రశ్నలు",
    "agentsOperational": "ఏజెంట్లు పనిచేస్తున్నారు",
    "avgCoordinationTime": "సగటు సమన్వయ సమయం",
    "emergenciesFlagged": "ఫ్లాగ్ చేయబడిన అత్యవసరాలు",
    "trendsHeader": "కమ్యూనిటీ హెల్త్ ఆందోళన పోకడలు",
    "trendsDesc": "జిల్లా ఆరోగ్య సంరక్షణ ప్రతిస్పందన కోసం అనామక లక్షణాల ట్రాకింగ్.",
    "cases": "కేసులు",
    "districtAlert": "జిల్లా హెచ్చరిక:",
    "districtAlertText": "మలేరియా/డెంగ్యూ సీజన్. కరీంనగర్/వరంగల్ జిల్లాల్లో దోమల నివారణ సూచించబడింది.",
    "recentConsultationsHeader": "మీ ఇటీవలి సంప్రదింపులు",
    "noConsultationsLogged": "ఇంకా ఎలాంటి సంప్రదింపులు నమోదు కాలేదు.",
    "startChattingTip": "మీ ఆరోగ్య అంచనాలను రూపొందించడానికి లైఫ్‌లైన్ AIతో చాట్ చేయడం ప్రారంభించండి.",
    "quickActions": "త్వరిత చర్యలు",
    "startSymptomCheckTitle": "లక్షణాలు తనిఖీ",
    "startSymptomCheckDesc": "మీ సమస్యను వివరించి మార్గదర్శకత్వాన్ని పొందండి.",
    "browseGovSchemesTitle": "ప్రభుత్వ పథకాలు",
    "browseGovSchemesDesc": "రాష్ట్ర & జాతీయ పథకాల కోసం అర్హతను తనిఖీ చేయండి.",
    "downloadOfflineDbTitle": "ఆఫ్‌లైన్ DB డౌన్‌లోడ్",
    "downloadOfflineDbDesc": "ఆరోగ్య సంరక్షణ జాబితాలను ఫోన్ నిల్వకు సేవ్ చేయండి.",
    "actionPlanHeader": "వ్యక్తిగతీకరించిన ఆరోగ్య కార్యాచరణ ప్రణాళిక",
    "urgencyLevel": "{urgency} అత్యవసరం",
    "emergencyResponse": "అత్యవసర క్లిష్టమైన ప్రతిస్పందన",
    "callAmbulance": "అంబులెన్స్‌ను పిలవండి",
    "immediateActions": "తక్షణ చర్యలు అవసరం:",
    "symptomAssessment": "లక్షణాలు & ఆరోగ్య అంచనా",
    "matchedSymptoms": "సరిపోలిన లక్షణాలు:",
    "possibleConditions": "సాధ్యమైన పరిస్థితులు:",
    "careInstructions": "సంరక్షణ సూచనలు:",
    "seekMedicalCareIf": "మీరు అనుభవిస్తే తక్షణ వైద్య సంరక్షణ పొందండి:",
    "nearbyFacilities": "సమీపంలోని ఆరోగ్య సంరక్షణ సౌకర్యాలు",
    "liveWebSearch": "లైవ్ వెబ్ శోధన 🌐",
    "beds": "పడకలు:",
    "emergency247": "అత్యవసర సేవలు 24/7",
    "ayushmanBharatTag": "ఆయుష్మాన్ భారత్",
    "govBenefits": "ప్రభుత్వ ఆరోగ్య ప్రయోజనాలు",
    "eligibilityStrong": "అర్హత:",
    "requiredDocs": "అవసరమైన పత్రాలు:",
    "medicineReference": "ఔషధ సూచన & విద్య",
    "usageLabel": "ఉపయోగం:",
    "dosageLabel": "మోతాదు:",
    "warningLabel": "హెచ్చరిక:",
    "generalMedGuidelines": "సాధారణ ఔషధ మార్గదర్శకాలు",
    "followupCare": "ఫాలో-అప్ కేర్ & టైమ్‌లైన్స్",
    "healthReminders": "ఆరోగ్య రిమైండర్ల టైమ్‌లైన్:",
    "monitoringChecklist": "ఆరోగ్య పర్యవేక్షణ చెక్‌లిస్ట్",
    "printActionPlan": "కార్యాచరణ ప్రణాళికను ప్రింట్ చేయండి",
    "saveToProfile": "ప్రొఫైల్‌కు సేవ్ చేయండి",
    "orchestrator": "ఆర్కెస్ట్రేటర్",
    "multiAgentPipeline": "మల్టీ-ఏజెంట్ పైప్‌లైన్",
    "analyzing": "విశ్లేషిస్తోంది...",
    "doneIn": "లో పూర్తయింది",
    "standby": "స్టాండ్‌బై",
    "parallelProcessingTip": "ఏజెంట్లు తెలివైన రూటింగ్‌తో సమాంతరంగా ప్రాసెస్ చేస్తారు"
  },
  "ta": {
    "welcome": "லைஃப்லைன் AI க்கு வரவேற்கிறோம்",
    "tagline": "உங்கள் AI-இயங்கும் சமூக சுகாதார உதவியாளர்",
    "askSymptoms": "உங்கள் அறிகுறிகளை விவரிக்கவும்",
    "emergency": "அவசரநிலை",
    "callEmergency": "அவசர சேவைகளை அழைக்கவும்",
    "nearbyHospitals": "அருகிலுள்ள மருத்துவமனைகள்",
    "govSchemes": "அரசு சுகாதார திட்டங்கள்",
    "medicines": "மருந்து தகவல்",
    "followUp": "பின்தொடர் கவனிப்பு",
    "actionPlan": "உங்கள் செயல் திட்டம்",
    "age": "வயது",
    "gender": "பாலினம்",
    "male": "ஆண்",
    "female": "பெண்",
    "other": "மற்றவை",
    "location": "இடம்",
    "submit": "சமர்ப்பிக்கவும்",
    "loading": "உங்கள் உடல்நிலையை பகுப்பாய்வு செய்கிறது...",
    "healthAssessment": "சுகாதார மதிப்பீடு",
    "urgencyLow": "குறைந்த அவசரம்",
    "urgencyMedium": "நடுத்தர அவசரம்",
    "urgencyHigh": "அதிக அவசரம்",
    "urgencyCritical": "ஆபத்தான - அவசரநிலை",
    "viewDetails": "விவரங்களைக் காண",
    "applyNow": "இப்போது விண்ணப்பிக்கவும்",
    "setReminder": "நினைவூட்டல் அமைக்கவும்",
    "translate": "மொழிபெயர்",
    "analytics": "சமூக பகுப்பாய்வு",
    "chat": "அரட்டை",
    "dashboard": "டாஷ்போர்டு",
    "profile": "சுயவிவரம்",
    "settings": "அமைப்புகள்",
    "languageSelect": "மொழியைத் தேர்ந்தெடுக்கவும்",
    "startConsultation": "ஆலோசனையைத் தொடங்கு",
    "disclaimer": "இது கல்வி நோக்கங்களுக்காக மட்டுமே.",
    "existingConditions": "ஏற்கனவே உள்ள நோய்கள்",
    "name": "பெயர்",
    "income": "ஆண்டு வருமானம்",
    "occupation": "தொழில்",
    "symptoms": "அறிகுறிகள்",
    "possibleCauses": "சாத்தியமான காரணங்கள்",
    "selfCare": "சுய பராமரிப்பு ஆலோசனை",
    "seekMedicalHelp": "மருத்துவ உதவி எப்போது பெறுவது",
    "eligibleSchemes": "தகுதியான திட்டங்கள்",
    "documentsRequired": "தேவையான ஆவணங்கள்",
    "howItWorks": "இது எப்படி வேலை செய்கிறது",
    "agents": "AI முகவர்கள்",
    "available": "கிடைக்கும்",
    "free": "இலவசம்",
    "home": "முகப்பு",
    "schemes": "திட்டங்கள்",
    "history": "வரலாறு",
    "logout": "வெளியேறு",
    "heroTitle": "லைஃப்லைன் AI உடன் பேசுங்கள் – புத்திசாலித்தனமான, வேகமான, சிறந்த",
    "tryItNow": "இப்போது முயற்சிக்கவும்",
    "getInTouch": "தொடர்பு கொள்ள",
    "contactDesc": "கேள்விகள் உள்ளதா அல்லது உதவி தேவையா? லைஃப்லைன் AI உதவ தயாராக உள்ளது. தொடர்பு கொள்ளுங்கள், விரைவில் உங்களை தொடர்புகொள்வோம்.",
    "contactUs": "எங்களைத் தொடர்பு கொள்ள",
    "email": "மின்னஞ்சல்",
    "all": "All",
    "cancel": "Cancel",
    "phone": "Phone",
    "warning": "Warning",
    "processing": "Processing...",
    "ready": "Ready",
    "active": "Active",
    "done": "Done",
    "total": "Total",
    "setYourProfile": "Set Your Profile",
    "locationNotSet": "Location not set",
    "quickProfile": "Quick Profile",
    "selectCity": "Select City",
    "saveProfile": "Save Profile",
    "schemesHeader": "Government Health Schemes Navigator",
    "schemesSubtitle": "Explore medical financial aid, maternity support, and free immunization plans.",
    "searchPlaceholder": "Search schemes by name or keywords...",
    "stateRegion": "State Region",
    "allIndia": "All India",
    "genderSpecific": "Gender Specific",
    "allGenders": "All Genders",
    "femaleOnly": "Female Only",
    "maleOnly": "Male Only",
    "benefitCategory": "Benefit Category",
    "foundSchemesCount": "Found {count} matching health benefit program(s)",
    "eligibilityCriteria": "Eligibility Criteria:",
    "incomeLimit": "Income Limit:",
    "ageGroup": "Age Group:",
    "genderTarget": "Gender target:",
    "applicableStates": "Applicable States:",
    "documentsNeeded": "Documents Needed to Apply:",
    "tollFree": "Toll-Free Helpline:",
    "applyOnline": "Apply Online ↗",
    "categoryGeneralHealth": "General Health",
    "categoryMaternalChild": "Maternal & Child Care",
    "categoryNutrition": "Nutrition",
    "categoryMentalHealth": "Mental Health",
    "categorySpecialized": "Specialized Procedures",
    "categoryInsurance": "Insurance & Security",
    "medicalHistoryTitle": "Medical History",
    "medicalHistorySubtitle": "Your past consultations and health records",
    "noConsultations": "No Consultations Yet",
    "noConsultationsDesc": "Your medical history will appear here after you complete your first AI-powered health consultation.",
    "startConsultationMH": "Start a Consultation",
    "clearHistory": "Clear History",
    "consultationCount": "{count} consultation",
    "consultationCountPlural": "{count} consultations",
    "clearHistoryConfirm": "Clear Medical History?",
    "clearHistoryDesc": "This will permanently delete all {count} consultation records. This action cannot be undone.",
    "clearHistoryDescSingle": "This will permanently delete your consultation record. This action cannot be undone.",
    "deleteAll": "Delete All",
    "symptomsLabel": "Symptoms:",
    "hideDetails": "Hide Details",
    "viewActionPlan": "View Action Plan",
    "communityTrendsHeader": "Community Health & Agent Analytics",
    "communityTrendsSubtitle": "Real-time statistics on AI system coordination and community concerns.",
    "totalHealthQueries": "Total Health Queries",
    "agentsOperational": "Agents Operational",
    "avgCoordinationTime": "Avg Coordination Time",
    "emergenciesFlagged": "Emergencies Flagged",
    "trendsHeader": "Community Health Concern Trends",
    "trendsDesc": "Anonymized symptom tracking for district healthcare response.",
    "cases": "cases",
    "districtAlert": "District Alert:",
    "districtAlertText": "Malaria/Dengue season. Mosquito control suggested in Karimnagar/Warangal districts.",
    "recentConsultationsHeader": "Your Recent Consultations",
    "noConsultationsLogged": "No consultations logged yet.",
    "startChattingTip": "Start chatting with LifeLine AI to generate your health assessments.",
    "quickActions": "Quick Actions",
    "startSymptomCheckTitle": "Start Symptom Check",
    "startSymptomCheckDesc": "Describe your issue and get guidance.",
    "browseGovSchemesTitle": "Browse Govt Schemes",
    "browseGovSchemesDesc": "Check eligibility for state & national plans.",
    "downloadOfflineDbTitle": "Download Offline DB",
    "downloadOfflineDbDesc": "Save healthcare listings to phone storage.",
    "actionPlanHeader": "Personalized Health Action Plan",
    "urgencyLevel": "{urgency} Urgency",
    "emergencyResponse": "Emergency Critical Response",
    "callAmbulance": "CALL AMBULANCE",
    "immediateActions": "Immediate Actions Required:",
    "symptomAssessment": "Symptom & Health Assessment",
    "matchedSymptoms": "Matched Symptoms:",
    "possibleConditions": "Possible Conditions:",
    "careInstructions": "Care Instructions:",
    "seekMedicalCareIf": "Seek immediate medical care if you experience:",
    "nearbyFacilities": "Nearby Healthcare Facilities",
    "liveWebSearch": "Live Web Search 🌐",
    "beds": "Beds:",
    "emergency247": "Emergency 24/7",
    "ayushmanBharatTag": "Ayushman Bharat",
    "govBenefits": "Government Health Benefits",
    "eligibilityStrong": "Eligibility:",
    "requiredDocs": "Required Documents:",
    "medicineReference": "Medicine Reference & Education",
    "usageLabel": "Usage:",
    "dosageLabel": "Dosage:",
    "warningLabel": "Warning:",
    "generalMedGuidelines": "General Medicine Guidelines",
    "followupCare": "Follow-up Care & Timelines",
    "healthReminders": "Health Reminders Timeline:",
    "monitoringChecklist": "Health Monitoring Checklist",
    "printActionPlan": "Print Action Plan",
    "saveToProfile": "Save to Profile",
    "orchestrator": "Orchestrator",
    "multiAgentPipeline": "Multi-Agent Pipeline",
    "analyzing": "Analyzing...",
    "doneIn": "Done in",
    "standby": "Standby",
    "parallelProcessingTip": "Agents process in parallel with intelligent routing"
  },
  "kn": {
    "welcome": "ಲೈಫ್‌ಲೈನ್ AI ಗೆ ಸ್ವಾಗತ",
    "tagline": "ನಿಮ್ಮ AI-ಚಾಲಿತ ಸಮುದಾಯ ಆರೋಗ್ಯ ಸಹಾಯಕ",
    "askSymptoms": "ನಿಮ್ಮ ರೋಗ ಲಕ್ಷಣಗಳನ್ನು ವಿವರಿಸಿ",
    "emergency": "ತುರ್ತು",
    "callEmergency": "ತುರ್ತು ಸೇವೆಗಳಿಗೆ ಕರೆ ಮಾಡಿ",
    "nearbyHospitals": "ಸಮೀಪದ ಆಸ್ಪತ್ರೆಗಳು",
    "govSchemes": "ಸರ್ಕಾರಿ ಆರೋಗ್ಯ ಯೋಜನೆಗಳು",
    "medicines": "ಔಷಧ ಮಾಹಿತಿ",
    "followUp": "ಅನುಸರಣಾ ಆರೈಕೆ",
    "actionPlan": "ನಿಮ್ಮ ಕ್ರಿಯಾ ಯೋಜನೆ",
    "age": "ವಯಸ್ಸು",
    "gender": "ಲಿಂಗ",
    "location": "ಸ್ಥಳ",
    "submit": "ಸಲ್ಲಿಸಿ",
    "loading": "ನಿಮ್ಮ ಆರೋಗ್ಯ ಕಾಳಜಿಯನ್ನು ವಿಶ್ಲೇಷಿಸಲಾಗುತ್ತಿದೆ...",
    "healthAssessment": "ಆರೋಗ್ಯ ಮೌಲ್ಯಮಾಪನ",
    "startConsultation": "ಸಮಾಲೋಚನೆ ಪ್ರಾರಂಭಿಸಿ",
    "disclaimer": "ಇದು ಶೈಕ್ಷಣಿಕ ಉದ್ದೇಶಗಳಿಗಾಗಿ ಮಾತ್ರ.",
    "chat": "ಚಾಟ್",
    "dashboard": "ಡ್ಯಾಶ್‌ಬೋರ್ಡ್",
    "free": "ಉಚಿತ",
    "home": "ಹೋಮ್",
    "schemes": "ಯೋಜನೆಗಳು",
    "history": "ಇತಿಹಾಸ",
    "logout": "ಲಾಗ್ ಔಟ್",
    "heroTitle": "ಲೈಫ್‌ಲೈನ್ AI ಜೊತೆಗೆ ಮಾತನಾಡಿ – ಹೆಚ್ಚು ಸ್ಮಾರ್ಟ್, ಹೆಚ್ಚು ವೇಗ, ಹೆಚ್ಚು ಉತ್ತಮ",
    "tryItNow": "ಈಗಲೇ ప్రయత్ನಿಸಿ",
    "getInTouch": "ಸಂಪರ್ಕಿಸಿ",
    "contactDesc": "ಪ್ರಶ್ನೆಗಳಿವೆಯೇ ಅಥವಾ ಸಹಾಯ ಬೇಕೇ? ಲೈಫ್‌ಲೈನ್ AI ಇಲ್ಲಿದೆ. ಸಂಪರ್કಿಸಿ ಮತ್ತು ನಾವು ಶೀಘ್ರದಲ್ಲೇ ಮರಳಿ ಸಂಪರ್ಕಿಸುತ್ತೇವೆ.",
    "contactUs": "ಸಂಪರ್ಕಿಸಿ",
    "email": "ಇಮೇಲ್",
    "all": "All",
    "cancel": "Cancel",
    "phone": "Phone",
    "warning": "Warning",
    "processing": "Processing...",
    "ready": "Ready",
    "active": "Active",
    "done": "Done",
    "total": "Total",
    "setYourProfile": "Set Your Profile",
    "locationNotSet": "Location not set",
    "quickProfile": "Quick Profile",
    "selectCity": "Select City",
    "saveProfile": "Save Profile",
    "schemesHeader": "Government Health Schemes Navigator",
    "schemesSubtitle": "Explore medical financial aid, maternity support, and free immunization plans.",
    "searchPlaceholder": "Search schemes by name or keywords...",
    "stateRegion": "State Region",
    "allIndia": "All India",
    "genderSpecific": "Gender Specific",
    "allGenders": "All Genders",
    "femaleOnly": "Female Only",
    "maleOnly": "Male Only",
    "benefitCategory": "Benefit Category",
    "foundSchemesCount": "Found {count} matching health benefit program(s)",
    "eligibilityCriteria": "Eligibility Criteria:",
    "incomeLimit": "Income Limit:",
    "ageGroup": "Age Group:",
    "genderTarget": "Gender target:",
    "applicableStates": "Applicable States:",
    "documentsNeeded": "Documents Needed to Apply:",
    "tollFree": "Toll-Free Helpline:",
    "applyOnline": "Apply Online ↗",
    "categoryGeneralHealth": "General Health",
    "categoryMaternalChild": "Maternal & Child Care",
    "categoryNutrition": "Nutrition",
    "categoryMentalHealth": "Mental Health",
    "categorySpecialized": "Specialized Procedures",
    "categoryInsurance": "Insurance & Security",
    "medicalHistoryTitle": "Medical History",
    "medicalHistorySubtitle": "Your past consultations and health records",
    "noConsultations": "No Consultations Yet",
    "noConsultationsDesc": "Your medical history will appear here after you complete your first AI-powered health consultation.",
    "startConsultationMH": "Start a Consultation",
    "clearHistory": "Clear History",
    "consultationCount": "{count} consultation",
    "consultationCountPlural": "{count} consultations",
    "clearHistoryConfirm": "Clear Medical History?",
    "clearHistoryDesc": "This will permanently delete all {count} consultation records. This action cannot be undone.",
    "clearHistoryDescSingle": "This will permanently delete your consultation record. This action cannot be undone.",
    "deleteAll": "Delete All",
    "symptomsLabel": "Symptoms:",
    "hideDetails": "Hide Details",
    "viewActionPlan": "View Action Plan",
    "communityTrendsHeader": "Community Health & Agent Analytics",
    "communityTrendsSubtitle": "Real-time statistics on AI system coordination and community concerns.",
    "totalHealthQueries": "Total Health Queries",
    "agentsOperational": "Agents Operational",
    "avgCoordinationTime": "Avg Coordination Time",
    "emergenciesFlagged": "Emergencies Flagged",
    "trendsHeader": "Community Health Concern Trends",
    "trendsDesc": "Anonymized symptom tracking for district healthcare response.",
    "cases": "cases",
    "districtAlert": "District Alert:",
    "districtAlertText": "Malaria/Dengue season. Mosquito control suggested in Karimnagar/Warangal districts.",
    "recentConsultationsHeader": "Your Recent Consultations",
    "noConsultationsLogged": "No consultations logged yet.",
    "startChattingTip": "Start chatting with LifeLine AI to generate your health assessments.",
    "quickActions": "Quick Actions",
    "startSymptomCheckTitle": "Start Symptom Check",
    "startSymptomCheckDesc": "Describe your issue and get guidance.",
    "browseGovSchemesTitle": "Browse Govt Schemes",
    "browseGovSchemesDesc": "Check eligibility for state & national plans.",
    "downloadOfflineDbTitle": "Download Offline DB",
    "downloadOfflineDbDesc": "Save healthcare listings to phone storage.",
    "actionPlanHeader": "Personalized Health Action Plan",
    "urgencyLevel": "{urgency} Urgency",
    "emergencyResponse": "Emergency Critical Response",
    "callAmbulance": "CALL AMBULANCE",
    "immediateActions": "Immediate Actions Required:",
    "symptomAssessment": "Symptom & Health Assessment",
    "matchedSymptoms": "Matched Symptoms:",
    "possibleConditions": "Possible Conditions:",
    "careInstructions": "Care Instructions:",
    "seekMedicalCareIf": "Seek immediate medical care if you experience:",
    "nearbyFacilities": "Nearby Healthcare Facilities",
    "liveWebSearch": "Live Web Search 🌐",
    "beds": "Beds:",
    "emergency247": "Emergency 24/7",
    "ayushmanBharatTag": "Ayushman Bharat",
    "govBenefits": "Government Health Benefits",
    "eligibilityStrong": "Eligibility:",
    "requiredDocs": "Required Documents:",
    "medicineReference": "Medicine Reference & Education",
    "usageLabel": "Usage:",
    "dosageLabel": "Dosage:",
    "warningLabel": "Warning:",
    "generalMedGuidelines": "General Medicine Guidelines",
    "followupCare": "Follow-up Care & Timelines",
    "healthReminders": "Health Reminders Timeline:",
    "monitoringChecklist": "Health Monitoring Checklist",
    "printActionPlan": "Print Action Plan",
    "saveToProfile": "Save to Profile",
    "orchestrator": "Orchestrator",
    "multiAgentPipeline": "Multi-Agent Pipeline",
    "analyzing": "Analyzing...",
    "doneIn": "Done in",
    "standby": "Standby",
    "parallelProcessingTip": "Agents process in parallel with intelligent routing"
  },
  "ml": {
    "welcome": "ലൈഫ്‌ലൈൻ AI ലേക്ക് സ്വാഗതം",
    "tagline": "നിങ്ങളുടെ AI-പ്രവർത്തിത സാമൂഹിക ആരോഗ്യ സഹായി",
    "askSymptoms": "നിങ്ങളുടെ ലക്ഷണങ്ങൾ വിവരിക്കുക",
    "emergency": "അടിയന്തരാവസ്ഥ",
    "callEmergency": "അടിയന്തര സേവനങ്ങളെ വിളിക്കുക",
    "nearbyHospitals": "സമീപത്തുള്ള ആശുപത്രികൾ",
    "govSchemes": "സർക്കാർ ആരോഗ്യ പദ്ധതികൾ",
    "medicines": "മരുന്ന് വിവരങ്ങൾ",
    "followUp": "ഫോളോ-അപ്പ് പരിചരണം",
    "actionPlan": "നിങ്ങളുടെ പ്രവർത്തന പദ്ധതി",
    "age": "പ്രായം",
    "gender": "ലിംഗം",
    "location": "സ്ഥലം",
    "submit": "സമർപ്പിക്കുക",
    "loading": "നിങ്ങളുടെ ആരോഗ്യ പ്രശ്നം വിശകലനം ചെയ്യുന്നു...",
    "healthAssessment": "ആരോഗ്യ വിലയിരുത്തൽ",
    "startConsultation": "കൺസൾട്ടേഷൻ ആരംഭിക്കുക",
    "disclaimer": "ഇത് വിദ്യാഭ്യാസ ആവശ്യങ്ങൾക്ക് മാത്രം.",
    "chat": "ചാറ്റ്",
    "dashboard": "ഡാഷ്‌ബോർഡ്",
    "free": "സൗജന്യം",
    "home": "ഹോം",
    "schemes": "പദ്ധതികൾ",
    "history": "ചരിത്രം",
    "logout": "ലോഗ് ഔട്ട്",
    "heroTitle": "ലൈഫ്‌ലൈൻ AI-യോട് സംസാരിക്കുക – കൂടുതൽ സ്മാർട്ട്, വേഗതയേറിയത്, മികച്ചത്",
    "tryItNow": "ഇപ്പോൾ ശ്രമിക്കുക",
    "getInTouch": "ബന്ധപ്പെടുക",
    "contactDesc": "ചോദ്യങ്ങളുണ്ടോ അതോ സഹായം ആവശ്യമുണ്ടോ? ലൈഫ്‌ലൈൻ AI ഇവിടെയുണ്ട്. ബന്ധപ്പെടുക, ഞങ്ങൾ ഉടൻ തിരികെ ബന്ധപ്പെടാം.",
    "contactUs": "ഞങ്ങളെ ബന്ധപ്പെടുക",
    "email": "ഇമെയിൽ",
    "all": "All",
    "cancel": "Cancel",
    "phone": "Phone",
    "warning": "Warning",
    "processing": "Processing...",
    "ready": "Ready",
    "active": "Active",
    "done": "Done",
    "total": "Total",
    "setYourProfile": "Set Your Profile",
    "locationNotSet": "Location not set",
    "quickProfile": "Quick Profile",
    "selectCity": "Select City",
    "saveProfile": "Save Profile",
    "schemesHeader": "Government Health Schemes Navigator",
    "schemesSubtitle": "Explore medical financial aid, maternity support, and free immunization plans.",
    "searchPlaceholder": "Search schemes by name or keywords...",
    "stateRegion": "State Region",
    "allIndia": "All India",
    "genderSpecific": "Gender Specific",
    "allGenders": "All Genders",
    "femaleOnly": "Female Only",
    "maleOnly": "Male Only",
    "benefitCategory": "Benefit Category",
    "foundSchemesCount": "Found {count} matching health benefit program(s)",
    "eligibilityCriteria": "Eligibility Criteria:",
    "incomeLimit": "Income Limit:",
    "ageGroup": "Age Group:",
    "genderTarget": "Gender target:",
    "applicableStates": "Applicable States:",
    "documentsNeeded": "Documents Needed to Apply:",
    "tollFree": "Toll-Free Helpline:",
    "applyOnline": "Apply Online ↗",
    "categoryGeneralHealth": "General Health",
    "categoryMaternalChild": "Maternal & Child Care",
    "categoryNutrition": "Nutrition",
    "categoryMentalHealth": "Mental Health",
    "categorySpecialized": "Specialized Procedures",
    "categoryInsurance": "Insurance & Security",
    "medicalHistoryTitle": "Medical History",
    "medicalHistorySubtitle": "Your past consultations and health records",
    "noConsultations": "No Consultations Yet",
    "noConsultationsDesc": "Your medical history will appear here after you complete your first AI-powered health consultation.",
    "startConsultationMH": "Start a Consultation",
    "clearHistory": "Clear History",
    "consultationCount": "{count} consultation",
    "consultationCountPlural": "{count} consultations",
    "clearHistoryConfirm": "Clear Medical History?",
    "clearHistoryDesc": "This will permanently delete all {count} consultation records. This action cannot be undone.",
    "clearHistoryDescSingle": "This will permanently delete your consultation record. This action cannot be undone.",
    "deleteAll": "Delete All",
    "symptomsLabel": "Symptoms:",
    "hideDetails": "Hide Details",
    "viewActionPlan": "View Action Plan",
    "communityTrendsHeader": "Community Health & Agent Analytics",
    "communityTrendsSubtitle": "Real-time statistics on AI system coordination and community concerns.",
    "totalHealthQueries": "Total Health Queries",
    "agentsOperational": "Agents Operational",
    "avgCoordinationTime": "Avg Coordination Time",
    "emergenciesFlagged": "Emergencies Flagged",
    "trendsHeader": "Community Health Concern Trends",
    "trendsDesc": "Anonymized symptom tracking for district healthcare response.",
    "cases": "cases",
    "districtAlert": "District Alert:",
    "districtAlertText": "Malaria/Dengue season. Mosquito control suggested in Karimnagar/Warangal districts.",
    "recentConsultationsHeader": "Your Recent Consultations",
    "noConsultationsLogged": "No consultations logged yet.",
    "startChattingTip": "Start chatting with LifeLine AI to generate your health assessments.",
    "quickActions": "Quick Actions",
    "startSymptomCheckTitle": "Start Symptom Check",
    "startSymptomCheckDesc": "Describe your issue and get guidance.",
    "browseGovSchemesTitle": "Browse Govt Schemes",
    "browseGovSchemesDesc": "Check eligibility for state & national plans.",
    "downloadOfflineDbTitle": "Download Offline DB",
    "downloadOfflineDbDesc": "Save healthcare listings to phone storage.",
    "actionPlanHeader": "Personalized Health Action Plan",
    "urgencyLevel": "{urgency} Urgency",
    "emergencyResponse": "Emergency Critical Response",
    "callAmbulance": "CALL AMBULANCE",
    "immediateActions": "Immediate Actions Required:",
    "symptomAssessment": "Symptom & Health Assessment",
    "matchedSymptoms": "Matched Symptoms:",
    "possibleConditions": "Possible Conditions:",
    "careInstructions": "Care Instructions:",
    "seekMedicalCareIf": "Seek immediate medical care if you experience:",
    "nearbyFacilities": "Nearby Healthcare Facilities",
    "liveWebSearch": "Live Web Search 🌐",
    "beds": "Beds:",
    "emergency247": "Emergency 24/7",
    "ayushmanBharatTag": "Ayushman Bharat",
    "govBenefits": "Government Health Benefits",
    "eligibilityStrong": "Eligibility:",
    "requiredDocs": "Required Documents:",
    "medicineReference": "Medicine Reference & Education",
    "usageLabel": "Usage:",
    "dosageLabel": "Dosage:",
    "warningLabel": "Warning:",
    "generalMedGuidelines": "General Medicine Guidelines",
    "followupCare": "Follow-up Care & Timelines",
    "healthReminders": "Health Reminders Timeline:",
    "monitoringChecklist": "Health Monitoring Checklist",
    "printActionPlan": "Print Action Plan",
    "saveToProfile": "Save to Profile",
    "orchestrator": "Orchestrator",
    "multiAgentPipeline": "Multi-Agent Pipeline",
    "analyzing": "Analyzing...",
    "doneIn": "Done in",
    "standby": "Standby",
    "parallelProcessingTip": "Agents process in parallel with intelligent routing"
  },
  "bn": {
    "welcome": "লাইফলাইন AI-তে স্বাগতম",
    "tagline": "আপনার AI-চালিত কমিউনিটি স্বাস্থ্য সহকারী",
    "askSymptoms": "আপনার উপসর্গ বর্ণনা করুন",
    "emergency": "জরুরি অবস্থা",
    "callEmergency": "জরুরি সেবায় কল করুন",
    "nearbyHospitals": "কাছের হাসপাতাল",
    "govSchemes": "সরকারি স্বাস্থ্য প্রকল্প",
    "medicines": "ওষুধের তথ্য",
    "followUp": "ফলো-আপ যত্ন",
    "actionPlan": "আপনার কর্ম পরিকল্পনা",
    "age": "বয়স",
    "gender": "লিঙ্গ",
    "location": "অবস্থান",
    "submit": "জমা দিন",
    "loading": "আপনার স্বাস্থ্য সমস্যা বিশ্লেষণ করা হচ্ছে...",
    "healthAssessment": "স্বাস্থ্য মূল্যায়ন",
    "startConsultation": "পরামর্শ শুরু করুন",
    "disclaimer": "এটি শুধুমাত্র শিক্ষামূলক উদ্দেশ্যে.",
    "chat": "চ্যাট",
    "dashboard": "ড্যাশবোর্ড",
    "free": "বিনামূল্যে",
    "home": "হোম",
    "schemes": "পরিকল্পনা",
    "history": "ইতিহাস",
    "logout": "লগ আউট",
    "heroTitle": "লাইফলাইন AI-এর সাথে কথা বলুন – স্মার্ট, দ্রুত, আরও ভালো",
    "tryItNow": "এখনই চেষ্টা করুন",
    "getInTouch": "যোগাযোগ করুন",
    "contactDesc": "কোনো প্রশ্ন আছে বা সাহায্য প্রয়োজন? লাইফলাইন AI সাহায্য করতে এখানে আছে। যোগাযোগ করুন এবং আমরা যত দ্রুত সম্ভব আপনার সাথে যোগাযোগ করব।",
    "contactUs": "আমাদের সাথে যোগাযোগ করুন",
    "email": "ইমেল",
    "all": "All",
    "cancel": "Cancel",
    "phone": "Phone",
    "warning": "Warning",
    "processing": "Processing...",
    "ready": "Ready",
    "active": "Active",
    "done": "Done",
    "total": "Total",
    "setYourProfile": "Set Your Profile",
    "locationNotSet": "Location not set",
    "quickProfile": "Quick Profile",
    "selectCity": "Select City",
    "saveProfile": "Save Profile",
    "schemesHeader": "Government Health Schemes Navigator",
    "schemesSubtitle": "Explore medical financial aid, maternity support, and free immunization plans.",
    "searchPlaceholder": "Search schemes by name or keywords...",
    "stateRegion": "State Region",
    "allIndia": "All India",
    "genderSpecific": "Gender Specific",
    "allGenders": "All Genders",
    "femaleOnly": "Female Only",
    "maleOnly": "Male Only",
    "benefitCategory": "Benefit Category",
    "foundSchemesCount": "Found {count} matching health benefit program(s)",
    "eligibilityCriteria": "Eligibility Criteria:",
    "incomeLimit": "Income Limit:",
    "ageGroup": "Age Group:",
    "genderTarget": "Gender target:",
    "applicableStates": "Applicable States:",
    "documentsNeeded": "Documents Needed to Apply:",
    "tollFree": "Toll-Free Helpline:",
    "applyOnline": "Apply Online ↗",
    "categoryGeneralHealth": "General Health",
    "categoryMaternalChild": "Maternal & Child Care",
    "categoryNutrition": "Nutrition",
    "categoryMentalHealth": "Mental Health",
    "categorySpecialized": "Specialized Procedures",
    "categoryInsurance": "Insurance & Security",
    "medicalHistoryTitle": "Medical History",
    "medicalHistorySubtitle": "Your past consultations and health records",
    "noConsultations": "No Consultations Yet",
    "noConsultationsDesc": "Your medical history will appear here after you complete your first AI-powered health consultation.",
    "startConsultationMH": "Start a Consultation",
    "clearHistory": "Clear History",
    "consultationCount": "{count} consultation",
    "consultationCountPlural": "{count} consultations",
    "clearHistoryConfirm": "Clear Medical History?",
    "clearHistoryDesc": "This will permanently delete all {count} consultation records. This action cannot be undone.",
    "clearHistoryDescSingle": "This will permanently delete your consultation record. This action cannot be undone.",
    "deleteAll": "Delete All",
    "symptomsLabel": "Symptoms:",
    "hideDetails": "Hide Details",
    "viewActionPlan": "View Action Plan",
    "communityTrendsHeader": "Community Health & Agent Analytics",
    "communityTrendsSubtitle": "Real-time statistics on AI system coordination and community concerns.",
    "totalHealthQueries": "Total Health Queries",
    "agentsOperational": "Agents Operational",
    "avgCoordinationTime": "Avg Coordination Time",
    "emergenciesFlagged": "Emergencies Flagged",
    "trendsHeader": "Community Health Concern Trends",
    "trendsDesc": "Anonymized symptom tracking for district healthcare response.",
    "cases": "cases",
    "districtAlert": "District Alert:",
    "districtAlertText": "Malaria/Dengue season. Mosquito control suggested in Karimnagar/Warangal districts.",
    "recentConsultationsHeader": "Your Recent Consultations",
    "noConsultationsLogged": "No consultations logged yet.",
    "startChattingTip": "Start chatting with LifeLine AI to generate your health assessments.",
    "quickActions": "Quick Actions",
    "startSymptomCheckTitle": "Start Symptom Check",
    "startSymptomCheckDesc": "Describe your issue and get guidance.",
    "browseGovSchemesTitle": "Browse Govt Schemes",
    "browseGovSchemesDesc": "Check eligibility for state & national plans.",
    "downloadOfflineDbTitle": "Download Offline DB",
    "downloadOfflineDbDesc": "Save healthcare listings to phone storage.",
    "actionPlanHeader": "Personalized Health Action Plan",
    "urgencyLevel": "{urgency} Urgency",
    "emergencyResponse": "Emergency Critical Response",
    "callAmbulance": "CALL AMBULANCE",
    "immediateActions": "Immediate Actions Required:",
    "symptomAssessment": "Symptom & Health Assessment",
    "matchedSymptoms": "Matched Symptoms:",
    "possibleConditions": "Possible Conditions:",
    "careInstructions": "Care Instructions:",
    "seekMedicalCareIf": "Seek immediate medical care if you experience:",
    "nearbyFacilities": "Nearby Healthcare Facilities",
    "liveWebSearch": "Live Web Search 🌐",
    "beds": "Beds:",
    "emergency247": "Emergency 24/7",
    "ayushmanBharatTag": "Ayushman Bharat",
    "govBenefits": "Government Health Benefits",
    "eligibilityStrong": "Eligibility:",
    "requiredDocs": "Required Documents:",
    "medicineReference": "Medicine Reference & Education",
    "usageLabel": "Usage:",
    "dosageLabel": "Dosage:",
    "warningLabel": "Warning:",
    "generalMedGuidelines": "General Medicine Guidelines",
    "followupCare": "Follow-up Care & Timelines",
    "healthReminders": "Health Reminders Timeline:",
    "monitoringChecklist": "Health Monitoring Checklist",
    "printActionPlan": "Print Action Plan",
    "saveToProfile": "Save to Profile",
    "orchestrator": "Orchestrator",
    "multiAgentPipeline": "Multi-Agent Pipeline",
    "analyzing": "Analyzing...",
    "doneIn": "Done in",
    "standby": "Standby",
    "parallelProcessingTip": "Agents process in parallel with intelligent routing"
  },
  "mr": {
    "welcome": "लाइफलाइन AI मध्ये आपले स्वागत आहे",
    "tagline": "तुमचा AI-चालित सामुदायिक आरोग्य सहाय्यक",
    "askSymptoms": "तुमच्या लक्षणांचे वर्णन करा",
    "emergency": "आणीबाणी",
    "callEmergency": "आणीबाणी सेवांना कॉल करा",
    "nearbyHospitals": "जवळचे रुग्णालये",
    "govSchemes": "सरकारी आरोग्य योजना",
    "medicines": "औषध माहिती",
    "followUp": "फॉलो-अप काळजी",
    "actionPlan": "तुमची कृती योजना",
    "age": "वय",
    "gender": "लिंग",
    "location": "स्थान",
    "submit": "सादर करा",
    "loading": "तुमच्या आरोग्य समस्येचे विश्लेषण...",
    "healthAssessment": "आरोग्य मूल्यांकन",
    "startConsultation": "सल्लामसलत सुरू करा",
    "disclaimer": "हे केवळ शैक्षणिक हेतूंसाठी आहे.",
    "chat": "चॅट",
    "dashboard": "डॅशबोर्ड",
    "free": "मोफत",
    "home": "होम",
    "schemes": "योजना",
    "history": "इतिहास",
    "logout": "लॉग आउट",
    "heroTitle": "लाइफलाईन AI शी बोला – अधिक स्मार्ट, वेगवान, उत्तम",
    "tryItNow": "आता प्रयत्न करा",
    "getInTouch": "संपर्क साधा",
    "contactDesc": "काही प्रश्न आहेत किंवा मदत हवी आहे? लाइफलाईन AI मदत करण्यासाठी येथे आहे. संपर्क साधा आणि आम्ही लवकरात लवकर तुमच्याशी संपर्क साधू.",
    "contactUs": "आमच्याशी संपर्क साधा",
    "email": "ईमेल",
    "all": "All",
    "cancel": "Cancel",
    "phone": "Phone",
    "warning": "Warning",
    "processing": "Processing...",
    "ready": "Ready",
    "active": "Active",
    "done": "Done",
    "total": "Total",
    "setYourProfile": "Set Your Profile",
    "locationNotSet": "Location not set",
    "quickProfile": "Quick Profile",
    "selectCity": "Select City",
    "saveProfile": "Save Profile",
    "schemesHeader": "Government Health Schemes Navigator",
    "schemesSubtitle": "Explore medical financial aid, maternity support, and free immunization plans.",
    "searchPlaceholder": "Search schemes by name or keywords...",
    "stateRegion": "State Region",
    "allIndia": "All India",
    "genderSpecific": "Gender Specific",
    "allGenders": "All Genders",
    "femaleOnly": "Female Only",
    "maleOnly": "Male Only",
    "benefitCategory": "Benefit Category",
    "foundSchemesCount": "Found {count} matching health benefit program(s)",
    "eligibilityCriteria": "Eligibility Criteria:",
    "incomeLimit": "Income Limit:",
    "ageGroup": "Age Group:",
    "genderTarget": "Gender target:",
    "applicableStates": "Applicable States:",
    "documentsNeeded": "Documents Needed to Apply:",
    "tollFree": "Toll-Free Helpline:",
    "applyOnline": "Apply Online ↗",
    "categoryGeneralHealth": "General Health",
    "categoryMaternalChild": "Maternal & Child Care",
    "categoryNutrition": "Nutrition",
    "categoryMentalHealth": "Mental Health",
    "categorySpecialized": "Specialized Procedures",
    "categoryInsurance": "Insurance & Security",
    "medicalHistoryTitle": "Medical History",
    "medicalHistorySubtitle": "Your past consultations and health records",
    "noConsultations": "No Consultations Yet",
    "noConsultationsDesc": "Your medical history will appear here after you complete your first AI-powered health consultation.",
    "startConsultationMH": "Start a Consultation",
    "clearHistory": "Clear History",
    "consultationCount": "{count} consultation",
    "consultationCountPlural": "{count} consultations",
    "clearHistoryConfirm": "Clear Medical History?",
    "clearHistoryDesc": "This will permanently delete all {count} consultation records. This action cannot be undone.",
    "clearHistoryDescSingle": "This will permanently delete your consultation record. This action cannot be undone.",
    "deleteAll": "Delete All",
    "symptomsLabel": "Symptoms:",
    "hideDetails": "Hide Details",
    "viewActionPlan": "View Action Plan",
    "communityTrendsHeader": "Community Health & Agent Analytics",
    "communityTrendsSubtitle": "Real-time statistics on AI system coordination and community concerns.",
    "totalHealthQueries": "Total Health Queries",
    "agentsOperational": "Agents Operational",
    "avgCoordinationTime": "Avg Coordination Time",
    "emergenciesFlagged": "Emergencies Flagged",
    "trendsHeader": "Community Health Concern Trends",
    "trendsDesc": "Anonymized symptom tracking for district healthcare response.",
    "cases": "cases",
    "districtAlert": "District Alert:",
    "districtAlertText": "Malaria/Dengue season. Mosquito control suggested in Karimnagar/Warangal districts.",
    "recentConsultationsHeader": "Your Recent Consultations",
    "noConsultationsLogged": "No consultations logged yet.",
    "startChattingTip": "Start chatting with LifeLine AI to generate your health assessments.",
    "quickActions": "Quick Actions",
    "startSymptomCheckTitle": "Start Symptom Check",
    "startSymptomCheckDesc": "Describe your issue and get guidance.",
    "browseGovSchemesTitle": "Browse Govt Schemes",
    "browseGovSchemesDesc": "Check eligibility for state & national plans.",
    "downloadOfflineDbTitle": "Download Offline DB",
    "downloadOfflineDbDesc": "Save healthcare listings to phone storage.",
    "actionPlanHeader": "Personalized Health Action Plan",
    "urgencyLevel": "{urgency} Urgency",
    "emergencyResponse": "Emergency Critical Response",
    "callAmbulance": "CALL AMBULANCE",
    "immediateActions": "Immediate Actions Required:",
    "symptomAssessment": "Symptom & Health Assessment",
    "matchedSymptoms": "Matched Symptoms:",
    "possibleConditions": "Possible Conditions:",
    "careInstructions": "Care Instructions:",
    "seekMedicalCareIf": "Seek immediate medical care if you experience:",
    "nearbyFacilities": "Nearby Healthcare Facilities",
    "liveWebSearch": "Live Web Search 🌐",
    "beds": "Beds:",
    "emergency247": "Emergency 24/7",
    "ayushmanBharatTag": "Ayushman Bharat",
    "govBenefits": "Government Health Benefits",
    "eligibilityStrong": "Eligibility:",
    "requiredDocs": "Required Documents:",
    "medicineReference": "Medicine Reference & Education",
    "usageLabel": "Usage:",
    "dosageLabel": "Dosage:",
    "warningLabel": "Warning:",
    "generalMedGuidelines": "General Medicine Guidelines",
    "followupCare": "Follow-up Care & Timelines",
    "healthReminders": "Health Reminders Timeline:",
    "monitoringChecklist": "Health Monitoring Checklist",
    "printActionPlan": "Print Action Plan",
    "saveToProfile": "Save to Profile",
    "orchestrator": "Orchestrator",
    "multiAgentPipeline": "Multi-Agent Pipeline",
    "analyzing": "Analyzing...",
    "doneIn": "Done in",
    "standby": "Standby",
    "parallelProcessingTip": "Agents process in parallel with intelligent routing"
  },
  "gu": {
    "welcome": "લાઇફલાઇન AI માં આપનું સ્વાગત છે",
    "tagline": "તમારો AI-સંચાલિત સમુદાય આરોગ્ય સહાયક",
    "askSymptoms": "તમારા લક્ષણો વર્ણવો",
    "emergency": "કટોકટી",
    "nearbyHospitals": "નજીકની હોસ્પિટલો",
    "govSchemes": "સરકારી આરોગ્ય યોજનાઓ",
    "medicines": "દવાની માહિતી",
    "actionPlan": "તમારી ક્રિયા યોજના",
    "age": "ઉંમર",
    "gender": "લિંગ",
    "location": "સ્થાન",
    "submit": "સબમિટ કરો",
    "loading": "તમારી આરોગ્ય ચિંતાનું વિશ્લેષણ...",
    "healthAssessment": "આરોગ્ય મૂલ્યાંકન",
    "startConsultation": "પરામર્શ શરૂ કરો",
    "chat": "ચેટ",
    "dashboard": "ડેશબોર્ડ",
    "free": "મફત",
    "home": "હોમ",
    "schemes": "યોજનાઓ",
    "history": "ઇતિહાસ",
    "logout": "લૉગ આઉટ",
    "heroTitle": "લાઇફલાઇન AI સાથે વાત કરો – વધુ સ્માર્ટ, ઝડપી, બહેતર",
    "tryItNow": "અત્યારે જ પ્રયત્ન કરો",
    "getInTouch": "સંપર્ક કરો",
    "contactDesc": "કોઈ પ્રશ્નો છે અથવા મદદની જરૂર છે? લાઇફલાઇન AI અહીં મદદ માટે છે. સંપર્ક કરો અને અમે શક્ય તેટલી વહેલી તકે તમારો સંપર્ક કરીશું.",
    "contactUs": "અમારો સંપર્ક કરો",
    "email": "ઈમેલ",
    "all": "All",
    "cancel": "Cancel",
    "phone": "Phone",
    "warning": "Warning",
    "processing": "Processing...",
    "ready": "Ready",
    "active": "Active",
    "done": "Done",
    "total": "Total",
    "setYourProfile": "Set Your Profile",
    "locationNotSet": "Location not set",
    "quickProfile": "Quick Profile",
    "selectCity": "Select City",
    "saveProfile": "Save Profile",
    "schemesHeader": "Government Health Schemes Navigator",
    "schemesSubtitle": "Explore medical financial aid, maternity support, and free immunization plans.",
    "searchPlaceholder": "Search schemes by name or keywords...",
    "stateRegion": "State Region",
    "allIndia": "All India",
    "genderSpecific": "Gender Specific",
    "allGenders": "All Genders",
    "femaleOnly": "Female Only",
    "maleOnly": "Male Only",
    "benefitCategory": "Benefit Category",
    "foundSchemesCount": "Found {count} matching health benefit program(s)",
    "eligibilityCriteria": "Eligibility Criteria:",
    "incomeLimit": "Income Limit:",
    "ageGroup": "Age Group:",
    "genderTarget": "Gender target:",
    "applicableStates": "Applicable States:",
    "documentsNeeded": "Documents Needed to Apply:",
    "tollFree": "Toll-Free Helpline:",
    "applyOnline": "Apply Online ↗",
    "categoryGeneralHealth": "General Health",
    "categoryMaternalChild": "Maternal & Child Care",
    "categoryNutrition": "Nutrition",
    "categoryMentalHealth": "Mental Health",
    "categorySpecialized": "Specialized Procedures",
    "categoryInsurance": "Insurance & Security",
    "medicalHistoryTitle": "Medical History",
    "medicalHistorySubtitle": "Your past consultations and health records",
    "noConsultations": "No Consultations Yet",
    "noConsultationsDesc": "Your medical history will appear here after you complete your first AI-powered health consultation.",
    "startConsultationMH": "Start a Consultation",
    "clearHistory": "Clear History",
    "consultationCount": "{count} consultation",
    "consultationCountPlural": "{count} consultations",
    "clearHistoryConfirm": "Clear Medical History?",
    "clearHistoryDesc": "This will permanently delete all {count} consultation records. This action cannot be undone.",
    "clearHistoryDescSingle": "This will permanently delete your consultation record. This action cannot be undone.",
    "deleteAll": "Delete All",
    "symptomsLabel": "Symptoms:",
    "hideDetails": "Hide Details",
    "viewActionPlan": "View Action Plan",
    "communityTrendsHeader": "Community Health & Agent Analytics",
    "communityTrendsSubtitle": "Real-time statistics on AI system coordination and community concerns.",
    "totalHealthQueries": "Total Health Queries",
    "agentsOperational": "Agents Operational",
    "avgCoordinationTime": "Avg Coordination Time",
    "emergenciesFlagged": "Emergencies Flagged",
    "trendsHeader": "Community Health Concern Trends",
    "trendsDesc": "Anonymized symptom tracking for district healthcare response.",
    "cases": "cases",
    "districtAlert": "District Alert:",
    "districtAlertText": "Malaria/Dengue season. Mosquito control suggested in Karimnagar/Warangal districts.",
    "recentConsultationsHeader": "Your Recent Consultations",
    "noConsultationsLogged": "No consultations logged yet.",
    "startChattingTip": "Start chatting with LifeLine AI to generate your health assessments.",
    "quickActions": "Quick Actions",
    "startSymptomCheckTitle": "Start Symptom Check",
    "startSymptomCheckDesc": "Describe your issue and get guidance.",
    "browseGovSchemesTitle": "Browse Govt Schemes",
    "browseGovSchemesDesc": "Check eligibility for state & national plans.",
    "downloadOfflineDbTitle": "Download Offline DB",
    "downloadOfflineDbDesc": "Save healthcare listings to phone storage.",
    "actionPlanHeader": "Personalized Health Action Plan",
    "urgencyLevel": "{urgency} Urgency",
    "emergencyResponse": "Emergency Critical Response",
    "callAmbulance": "CALL AMBULANCE",
    "immediateActions": "Immediate Actions Required:",
    "symptomAssessment": "Symptom & Health Assessment",
    "matchedSymptoms": "Matched Symptoms:",
    "possibleConditions": "Possible Conditions:",
    "careInstructions": "Care Instructions:",
    "seekMedicalCareIf": "Seek immediate medical care if you experience:",
    "nearbyFacilities": "Nearby Healthcare Facilities",
    "liveWebSearch": "Live Web Search 🌐",
    "beds": "Beds:",
    "emergency247": "Emergency 24/7",
    "ayushmanBharatTag": "Ayushman Bharat",
    "govBenefits": "Government Health Benefits",
    "eligibilityStrong": "Eligibility:",
    "requiredDocs": "Required Documents:",
    "medicineReference": "Medicine Reference & Education",
    "usageLabel": "Usage:",
    "dosageLabel": "Dosage:",
    "warningLabel": "Warning:",
    "generalMedGuidelines": "General Medicine Guidelines",
    "followupCare": "Follow-up Care & Timelines",
    "healthReminders": "Health Reminders Timeline:",
    "monitoringChecklist": "Health Monitoring Checklist",
    "printActionPlan": "Print Action Plan",
    "saveToProfile": "Save to Profile",
    "orchestrator": "Orchestrator",
    "multiAgentPipeline": "Multi-Agent Pipeline",
    "analyzing": "Analyzing...",
    "doneIn": "Done in",
    "standby": "Standby",
    "parallelProcessingTip": "Agents process in parallel with intelligent routing"
  },
  "pa": {
    "welcome": "ਲਾਈਫਲਾਈਨ AI ਵਿੱਚ ਜੀ ਆਇਆਂ ਨੂੰ",
    "tagline": "ਤੁਹਾਡਾ AI-ਸੰਚਾਲਿਤ ਕਮਿਊਨਿਟੀ ਸਿਹਤ ਸਹਾਇਕ",
    "askSymptoms": "ਆਪਣੇ ਲੱਛਣ ਦੱਸੋ",
    "emergency": "ਐਮਰਜੈਂਸੀ",
    "nearbyHospitals": "ਨੇੜੇ ਦੇ ਹਸਪਤਾਲ",
    "govSchemes": "ਸਰਕਾਰੀ ਸਿਹਤ ਯੋਜਨਾਵਾਂ",
    "medicines": "ਦਵਾਈ ਦੀ ਜਾਣਕਾਰੀ",
    "actionPlan": "ਤੁਹਾਡੀ ਕਾਰਜ ਯੋਜਨਾ",
    "age": "ਉਮਰ",
    "gender": "ਲਿੰਗ",
    "location": "ਟਿਕਾਣਾ",
    "submit": "ਜਮ੍ਹਾ ਕਰੋ",
    "loading": "ਤੁਹਾਡੀ ਸਿਹਤ ਸਮੱਸਿਆ ਦਾ ਵਿਸ਼ਲੇਸ਼ਣ...",
    "healthAssessment": "ਸਿਹਤ ਮੁਲਾਂਕਣ",
    "startConsultation": "ਸਲਾਹ ਸ਼ੁਰੂ ਕਰੋ",
    "chat": "ਚੈਟ",
    "dashboard": "ਡੈਸ਼ਬੋਰਡ",
    "free": "ਮੁਫ਼ਤ",
    "home": "ਹੋਮ",
    "schemes": "ਸਕੀਮਾਂ",
    "history": "ਇਤਿਹਾਸ",
    "logout": "ਲੌਗ ਆਉਟ",
    "heroTitle": "ਲਾਈਫਲਾਈਨ AI ਨਾਲ ਗੱਲ ਕਰੋ – ਵਧੇਰੇ ਸਮਾਰਟ, ਤੇਜ਼, ਬਿਹਤਰ",
    "tryItNow": "ਹੁਣੇ ਅਜ਼ਮਾਓ",
    "getInTouch": "ਸੰਪਰਕ ਕਰੋ",
    "contactDesc": "ਕੋਈ ਸਵਾਲ ਹਨ ਜਾਂ ਸਹਾਇਤਾ ਦੀ ਲੋੜ ਹੈ? ਲਾਈਫਲਾਈਨ AI ਮਦਦ ਲਈ ਇੱਥੇ ਹੈ। ਸੰਪਰਕ ਕਰੋ ਅਤੇ ਅਸੀਂ ਜਲਦੀ ਤੋਂ ਜਲਦੀ ਤੁਹਾਡੇ ਨਾਲ ਸੰਪਰਕ ਕਰਾਂਗੇ।",
    "contactUs": "ਸਾਡੇ ਨਾਲ ਸੰਪਰਕ ਕਰੋ",
    "email": "ਈਮੇਲ",
    "all": "All",
    "cancel": "Cancel",
    "phone": "Phone",
    "warning": "Warning",
    "processing": "Processing...",
    "ready": "Ready",
    "active": "Active",
    "done": "Done",
    "total": "Total",
    "setYourProfile": "Set Your Profile",
    "locationNotSet": "Location not set",
    "quickProfile": "Quick Profile",
    "selectCity": "Select City",
    "saveProfile": "Save Profile",
    "schemesHeader": "Government Health Schemes Navigator",
    "schemesSubtitle": "Explore medical financial aid, maternity support, and free immunization plans.",
    "searchPlaceholder": "Search schemes by name or keywords...",
    "stateRegion": "State Region",
    "allIndia": "All India",
    "genderSpecific": "Gender Specific",
    "allGenders": "All Genders",
    "femaleOnly": "Female Only",
    "maleOnly": "Male Only",
    "benefitCategory": "Benefit Category",
    "foundSchemesCount": "Found {count} matching health benefit program(s)",
    "eligibilityCriteria": "Eligibility Criteria:",
    "incomeLimit": "Income Limit:",
    "ageGroup": "Age Group:",
    "genderTarget": "Gender target:",
    "applicableStates": "Applicable States:",
    "documentsNeeded": "Documents Needed to Apply:",
    "tollFree": "Toll-Free Helpline:",
    "applyOnline": "Apply Online ↗",
    "categoryGeneralHealth": "General Health",
    "categoryMaternalChild": "Maternal & Child Care",
    "categoryNutrition": "Nutrition",
    "categoryMentalHealth": "Mental Health",
    "categorySpecialized": "Specialized Procedures",
    "categoryInsurance": "Insurance & Security",
    "medicalHistoryTitle": "Medical History",
    "medicalHistorySubtitle": "Your past consultations and health records",
    "noConsultations": "No Consultations Yet",
    "noConsultationsDesc": "Your medical history will appear here after you complete your first AI-powered health consultation.",
    "startConsultationMH": "Start a Consultation",
    "clearHistory": "Clear History",
    "consultationCount": "{count} consultation",
    "consultationCountPlural": "{count} consultations",
    "clearHistoryConfirm": "Clear Medical History?",
    "clearHistoryDesc": "This will permanently delete all {count} consultation records. This action cannot be undone.",
    "clearHistoryDescSingle": "This will permanently delete your consultation record. This action cannot be undone.",
    "deleteAll": "Delete All",
    "symptomsLabel": "Symptoms:",
    "hideDetails": "Hide Details",
    "viewActionPlan": "View Action Plan",
    "communityTrendsHeader": "Community Health & Agent Analytics",
    "communityTrendsSubtitle": "Real-time statistics on AI system coordination and community concerns.",
    "totalHealthQueries": "Total Health Queries",
    "agentsOperational": "Agents Operational",
    "avgCoordinationTime": "Avg Coordination Time",
    "emergenciesFlagged": "Emergencies Flagged",
    "trendsHeader": "Community Health Concern Trends",
    "trendsDesc": "Anonymized symptom tracking for district healthcare response.",
    "cases": "cases",
    "districtAlert": "District Alert:",
    "districtAlertText": "Malaria/Dengue season. Mosquito control suggested in Karimnagar/Warangal districts.",
    "recentConsultationsHeader": "Your Recent Consultations",
    "noConsultationsLogged": "No consultations logged yet.",
    "startChattingTip": "Start chatting with LifeLine AI to generate your health assessments.",
    "quickActions": "Quick Actions",
    "startSymptomCheckTitle": "Start Symptom Check",
    "startSymptomCheckDesc": "Describe your issue and get guidance.",
    "browseGovSchemesTitle": "Browse Govt Schemes",
    "browseGovSchemesDesc": "Check eligibility for state & national plans.",
    "downloadOfflineDbTitle": "Download Offline DB",
    "downloadOfflineDbDesc": "Save healthcare listings to phone storage.",
    "actionPlanHeader": "Personalized Health Action Plan",
    "urgencyLevel": "{urgency} Urgency",
    "emergencyResponse": "Emergency Critical Response",
    "callAmbulance": "CALL AMBULANCE",
    "immediateActions": "Immediate Actions Required:",
    "symptomAssessment": "Symptom & Health Assessment",
    "matchedSymptoms": "Matched Symptoms:",
    "possibleConditions": "Possible Conditions:",
    "careInstructions": "Care Instructions:",
    "seekMedicalCareIf": "Seek immediate medical care if you experience:",
    "nearbyFacilities": "Nearby Healthcare Facilities",
    "liveWebSearch": "Live Web Search 🌐",
    "beds": "Beds:",
    "emergency247": "Emergency 24/7",
    "ayushmanBharatTag": "Ayushman Bharat",
    "govBenefits": "Government Health Benefits",
    "eligibilityStrong": "Eligibility:",
    "requiredDocs": "Required Documents:",
    "medicineReference": "Medicine Reference & Education",
    "usageLabel": "Usage:",
    "dosageLabel": "Dosage:",
    "warningLabel": "Warning:",
    "generalMedGuidelines": "General Medicine Guidelines",
    "followupCare": "Follow-up Care & Timelines",
    "healthReminders": "Health Reminders Timeline:",
    "monitoringChecklist": "Health Monitoring Checklist",
    "printActionPlan": "Print Action Plan",
    "saveToProfile": "Save to Profile",
    "orchestrator": "Orchestrator",
    "multiAgentPipeline": "Multi-Agent Pipeline",
    "analyzing": "Analyzing...",
    "doneIn": "Done in",
    "standby": "Standby",
    "parallelProcessingTip": "Agents process in parallel with intelligent routing"
  },
  "or": {
    "welcome": "ଲାଇଫଲାଇନ AI କୁ ସ୍ୱାଗତ",
    "tagline": "ଆପଣଙ୍କ AI-ଚାଳିତ ସାମୁଦାୟିକ ସ୍ୱାସ୍ଥ୍ୟ ସହାୟକ",
    "askSymptoms": "ଆପଣଙ୍କ ଲକ୍ଷଣ ବର୍ଣ୍ଣନା କରନ୍ତୁ",
    "emergency": "ଜରୁରୀକାଳୀନ",
    "nearbyHospitals": "ନିକଟସ୍ଥ ହସ୍ପିଟାଲ",
    "govSchemes": "ସରକାରୀ ସ୍ୱାସ୍ଥ୍ୟ ଯୋଜନା",
    "medicines": "ଔଷଧ ସୂଚନା",
    "actionPlan": "ଆପଣଙ୍କ କାର୍ଯ୍ୟ ଯୋଜନା",
    "age": "ବୟସ",
    "gender": "ଲିଙ୍ଗ",
    "location": "ସ୍ଥାନ",
    "submit": "ଦାଖଲ କରନ୍ତୁ",
    "loading": "ଆପଣଙ୍କ ସ୍ୱାସ୍ଥ୍ୟ ସମସ୍ୟା ବିଶ୍ଳେଷଣ...",
    "healthAssessment": "ସ୍ୱାସ୍ଥ୍ୟ ମୂଲ୍ୟାଙ୍କନ",
    "startConsultation": "ପରାମର୍ଶ ଆରମ୍ଭ କରନ୍ତୁ",
    "chat": "ଚାଟ୍",
    "dashboard": "ଡ୍ୟାସବୋର୍ଡ",
    "free": "ମାଗଣା",
    "home": "ହୋମ୍",
    "schemes": "ଯୋଜନା",
    "history": "ଇତିହାସ",
    "logout": "ଲଗ୍ ଆଉଟ୍",
    "heroTitle": "ଲାଇଫଲାଇନ AI ସହିତ କଥା ହୁଅନ୍ତୁ – ଅଧିକ ସ୍ମାର୍ଟ, ଦ୍ରୁତ, ଉତ୍ତମ",
    "tryItNow": "ବର୍ତ୍ତମାନ ଚେଷ୍ଟା କରନ୍ତୁ",
    "getInTouch": "ଯୋଗାଯୋଗ କରନ୍ତୁ",
    "contactDesc": "କୌଣସି ପ୍ରଶ୍ନ ଅଛି କିମ୍ବା ସାହାଯ୍ୟ ଦରକାର? ଲାଇଫଲାଇନ AI ସାହାଯ୍ୟ କରିବାକୁ ଏଠାରେ ଅଛି | ଯୋଗାଯୋଗ କରନ୍ତು ଏବଂ ଆମେ ଯଥାଶୀଘ୍ର ଆପଣଙ୍କ ସହ ଯୋଗାଯୋଗ କରିବୁ |",
    "contactUs": "ଆମ ସହିତ ଯୋଗାଯୋਗ କରନ୍ତୁ",
    "email": "ଇମେଲ୍",
    "all": "All",
    "cancel": "Cancel",
    "phone": "Phone",
    "warning": "Warning",
    "processing": "Processing...",
    "ready": "Ready",
    "active": "Active",
    "done": "Done",
    "total": "Total",
    "setYourProfile": "Set Your Profile",
    "locationNotSet": "Location not set",
    "quickProfile": "Quick Profile",
    "selectCity": "Select City",
    "saveProfile": "Save Profile",
    "schemesHeader": "Government Health Schemes Navigator",
    "schemesSubtitle": "Explore medical financial aid, maternity support, and free immunization plans.",
    "searchPlaceholder": "Search schemes by name or keywords...",
    "stateRegion": "State Region",
    "allIndia": "All India",
    "genderSpecific": "Gender Specific",
    "allGenders": "All Genders",
    "femaleOnly": "Female Only",
    "maleOnly": "Male Only",
    "benefitCategory": "Benefit Category",
    "foundSchemesCount": "Found {count} matching health benefit program(s)",
    "eligibilityCriteria": "Eligibility Criteria:",
    "incomeLimit": "Income Limit:",
    "ageGroup": "Age Group:",
    "genderTarget": "Gender target:",
    "applicableStates": "Applicable States:",
    "documentsNeeded": "Documents Needed to Apply:",
    "tollFree": "Toll-Free Helpline:",
    "applyOnline": "Apply Online ↗",
    "categoryGeneralHealth": "General Health",
    "categoryMaternalChild": "Maternal & Child Care",
    "categoryNutrition": "Nutrition",
    "categoryMentalHealth": "Mental Health",
    "categorySpecialized": "Specialized Procedures",
    "categoryInsurance": "Insurance & Security",
    "medicalHistoryTitle": "Medical History",
    "medicalHistorySubtitle": "Your past consultations and health records",
    "noConsultations": "No Consultations Yet",
    "noConsultationsDesc": "Your medical history will appear here after you complete your first AI-powered health consultation.",
    "startConsultationMH": "Start a Consultation",
    "clearHistory": "Clear History",
    "consultationCount": "{count} consultation",
    "consultationCountPlural": "{count} consultations",
    "clearHistoryConfirm": "Clear Medical History?",
    "clearHistoryDesc": "This will permanently delete all {count} consultation records. This action cannot be undone.",
    "clearHistoryDescSingle": "This will permanently delete your consultation record. This action cannot be undone.",
    "deleteAll": "Delete All",
    "symptomsLabel": "Symptoms:",
    "hideDetails": "Hide Details",
    "viewActionPlan": "View Action Plan",
    "communityTrendsHeader": "Community Health & Agent Analytics",
    "communityTrendsSubtitle": "Real-time statistics on AI system coordination and community concerns.",
    "totalHealthQueries": "Total Health Queries",
    "agentsOperational": "Agents Operational",
    "avgCoordinationTime": "Avg Coordination Time",
    "emergenciesFlagged": "Emergencies Flagged",
    "trendsHeader": "Community Health Concern Trends",
    "trendsDesc": "Anonymized symptom tracking for district healthcare response.",
    "cases": "cases",
    "districtAlert": "District Alert:",
    "districtAlertText": "Malaria/Dengue season. Mosquito control suggested in Karimnagar/Warangal districts.",
    "recentConsultationsHeader": "Your Recent Consultations",
    "noConsultationsLogged": "No consultations logged yet.",
    "startChattingTip": "Start chatting with LifeLine AI to generate your health assessments.",
    "quickActions": "Quick Actions",
    "startSymptomCheckTitle": "Start Symptom Check",
    "startSymptomCheckDesc": "Describe your issue and get guidance.",
    "browseGovSchemesTitle": "Browse Govt Schemes",
    "browseGovSchemesDesc": "Check eligibility for state & national plans.",
    "downloadOfflineDbTitle": "Download Offline DB",
    "downloadOfflineDbDesc": "Save healthcare listings to phone storage.",
    "actionPlanHeader": "Personalized Health Action Plan",
    "urgencyLevel": "{urgency} Urgency",
    "emergencyResponse": "Emergency Critical Response",
    "callAmbulance": "CALL AMBULANCE",
    "immediateActions": "Immediate Actions Required:",
    "symptomAssessment": "Symptom & Health Assessment",
    "matchedSymptoms": "Matched Symptoms:",
    "possibleConditions": "Possible Conditions:",
    "careInstructions": "Care Instructions:",
    "seekMedicalCareIf": "Seek immediate medical care if you experience:",
    "nearbyFacilities": "Nearby Healthcare Facilities",
    "liveWebSearch": "Live Web Search 🌐",
    "beds": "Beds:",
    "emergency247": "Emergency 24/7",
    "ayushmanBharatTag": "Ayushman Bharat",
    "govBenefits": "Government Health Benefits",
    "eligibilityStrong": "Eligibility:",
    "requiredDocs": "Required Documents:",
    "medicineReference": "Medicine Reference & Education",
    "usageLabel": "Usage:",
    "dosageLabel": "Dosage:",
    "warningLabel": "Warning:",
    "generalMedGuidelines": "General Medicine Guidelines",
    "followupCare": "Follow-up Care & Timelines",
    "healthReminders": "Health Reminders Timeline:",
    "monitoringChecklist": "Health Monitoring Checklist",
    "printActionPlan": "Print Action Plan",
    "saveToProfile": "Save to Profile",
    "orchestrator": "Orchestrator",
    "multiAgentPipeline": "Multi-Agent Pipeline",
    "analyzing": "Analyzing...",
    "doneIn": "Done in",
    "standby": "Standby",
    "parallelProcessingTip": "Agents process in parallel with intelligent routing"
  },
  "ur": {
    "welcome": "لائف لائن AI میں خوش آمدید",
    "tagline": "آپ کا AI سے چلنے والا کمیونٹی ہیلتھ اسسٹنٹ",
    "askSymptoms": "اپنی علامات بیان کریں",
    "emergency": "ایمرجنسی",
    "callEmergency": "ایمرجنسی سروسز کو کال کریں",
    "nearbyHospitals": "قریبی ہسپتال",
    "govSchemes": "سرکاری صحت اسکیمیں",
    "medicines": "دوائی کی معلومات",
    "followUp": "فالو اپ دیکھ بھال",
    "actionPlan": "آپ کا ایکشن پلان",
    "age": "عمر",
    "gender": "جنس",
    "location": "مقام",
    "submit": "جمع کرائیں",
    "loading": "آپ کی صحت کی تشویش کا تجزیہ...",
    "healthAssessment": "صحت کی تشخیص",
    "startConsultation": "مشاورت شروع کریں",
    "disclaimer": "یہ صرف تعلیمی مقاصد کے لیے ہے۔",
    "chat": "چیٹ",
    "dashboard": "دیش بورڈ",
    "free": "مفت",
    "home": "ہوم",
    "schemes": "اسکیمیں",
    "history": "تاریخ",
    "logout": "لاگ آؤٹ",
    "heroTitle": "لائف لائن AI سے بات کریں – ہوشیار، تیز، بہتر",
    "tryItNow": "ابھی کوشش کریں",
    "getInTouch": "رابطہ کریں",
    "contactDesc": "کیا آپ کے پاس کوئی سوالات ہیں یا مدد کی ضرورت ہے؟ لائف لائن AI مدد کے لیے حاضر ہے۔ رابطہ کریں اور ہم جلد از جلد آپ سے رابطہ کریں گے۔",
    "contactUs": "ہم سے رابطہ کریں",
    "email": "ای میل",
    "all": "All",
    "cancel": "Cancel",
    "phone": "Phone",
    "warning": "Warning",
    "processing": "Processing...",
    "ready": "Ready",
    "active": "Active",
    "done": "Done",
    "total": "Total",
    "setYourProfile": "Set Your Profile",
    "locationNotSet": "Location not set",
    "quickProfile": "Quick Profile",
    "selectCity": "Select City",
    "saveProfile": "Save Profile",
    "schemesHeader": "Government Health Schemes Navigator",
    "schemesSubtitle": "Explore medical financial aid, maternity support, and free immunization plans.",
    "searchPlaceholder": "Search schemes by name or keywords...",
    "stateRegion": "State Region",
    "allIndia": "All India",
    "genderSpecific": "Gender Specific",
    "allGenders": "All Genders",
    "femaleOnly": "Female Only",
    "maleOnly": "Male Only",
    "benefitCategory": "Benefit Category",
    "foundSchemesCount": "Found {count} matching health benefit program(s)",
    "eligibilityCriteria": "Eligibility Criteria:",
    "incomeLimit": "Income Limit:",
    "ageGroup": "Age Group:",
    "genderTarget": "Gender target:",
    "applicableStates": "Applicable States:",
    "documentsNeeded": "Documents Needed to Apply:",
    "tollFree": "Toll-Free Helpline:",
    "applyOnline": "Apply Online ↗",
    "categoryGeneralHealth": "General Health",
    "categoryMaternalChild": "Maternal & Child Care",
    "categoryNutrition": "Nutrition",
    "categoryMentalHealth": "Mental Health",
    "categorySpecialized": "Specialized Procedures",
    "categoryInsurance": "Insurance & Security",
    "medicalHistoryTitle": "Medical History",
    "medicalHistorySubtitle": "Your past consultations and health records",
    "noConsultations": "No Consultations Yet",
    "noConsultationsDesc": "Your medical history will appear here after you complete your first AI-powered health consultation.",
    "startConsultationMH": "Start a Consultation",
    "clearHistory": "Clear History",
    "consultationCount": "{count} consultation",
    "consultationCountPlural": "{count} consultations",
    "clearHistoryConfirm": "Clear Medical History?",
    "clearHistoryDesc": "This will permanently delete all {count} consultation records. This action cannot be undone.",
    "clearHistoryDescSingle": "This will permanently delete your consultation record. This action cannot be undone.",
    "deleteAll": "Delete All",
    "symptomsLabel": "Symptoms:",
    "hideDetails": "Hide Details",
    "viewActionPlan": "View Action Plan",
    "communityTrendsHeader": "Community Health & Agent Analytics",
    "communityTrendsSubtitle": "Real-time statistics on AI system coordination and community concerns.",
    "totalHealthQueries": "Total Health Queries",
    "agentsOperational": "Agents Operational",
    "avgCoordinationTime": "Avg Coordination Time",
    "emergenciesFlagged": "Emergencies Flagged",
    "trendsHeader": "Community Health Concern Trends",
    "trendsDesc": "Anonymized symptom tracking for district healthcare response.",
    "cases": "cases",
    "districtAlert": "District Alert:",
    "districtAlertText": "Malaria/Dengue season. Mosquito control suggested in Karimnagar/Warangal districts.",
    "recentConsultationsHeader": "Your Recent Consultations",
    "noConsultationsLogged": "No consultations logged yet.",
    "startChattingTip": "Start chatting with LifeLine AI to generate your health assessments.",
    "quickActions": "Quick Actions",
    "startSymptomCheckTitle": "Start Symptom Check",
    "startSymptomCheckDesc": "Describe your issue and get guidance.",
    "browseGovSchemesTitle": "Browse Govt Schemes",
    "browseGovSchemesDesc": "Check eligibility for state & national plans.",
    "downloadOfflineDbTitle": "Download Offline DB",
    "downloadOfflineDbDesc": "Save healthcare listings to phone storage.",
    "actionPlanHeader": "Personalized Health Action Plan",
    "urgencyLevel": "{urgency} Urgency",
    "emergencyResponse": "Emergency Critical Response",
    "callAmbulance": "CALL AMBULANCE",
    "immediateActions": "Immediate Actions Required:",
    "symptomAssessment": "Symptom & Health Assessment",
    "matchedSymptoms": "Matched Symptoms:",
    "possibleConditions": "Possible Conditions:",
    "careInstructions": "Care Instructions:",
    "seekMedicalCareIf": "Seek immediate medical care if you experience:",
    "nearbyFacilities": "Nearby Healthcare Facilities",
    "liveWebSearch": "Live Web Search 🌐",
    "beds": "Beds:",
    "emergency247": "Emergency 24/7",
    "ayushmanBharatTag": "Ayushman Bharat",
    "govBenefits": "Government Health Benefits",
    "eligibilityStrong": "Eligibility:",
    "requiredDocs": "Required Documents:",
    "medicineReference": "Medicine Reference & Education",
    "usageLabel": "Usage:",
    "dosageLabel": "Dosage:",
    "warningLabel": "Warning:",
    "generalMedGuidelines": "General Medicine Guidelines",
    "followupCare": "Follow-up Care & Timelines",
    "healthReminders": "Health Reminders Timeline:",
    "monitoringChecklist": "Health Monitoring Checklist",
    "printActionPlan": "Print Action Plan",
    "saveToProfile": "Save to Profile",
    "orchestrator": "Orchestrator",
    "multiAgentPipeline": "Multi-Agent Pipeline",
    "analyzing": "Analyzing...",
    "doneIn": "Done in",
    "standby": "Standby",
    "parallelProcessingTip": "Agents process in parallel with intelligent routing"
  }
}